[
    {
        "isinCd": "KR7210120002",
        "srtnCd": "A210120",
        "itmsNm": "\ube45\ud150\uce20",
        "trd_dd": "2015-01-02",
        "trdcnt1": "0",
        "trdcnt2": "0",
        "trdcnt3": "0",
        "trdcnt4": "0",
        "trdcnt5": "0",
        "trdcnt6": "0",
        "trdcnt7": "0",
        "trdcnt8": "0",
        "trdcnt9": "0",
        "trdcnt10": "0",
        "trdcnt11": "0",
        "trdcnt_tot": "0",
        "current_datetime": "2024-07-24 20:28:01.528841"
    },
    {
        "isinCd": "KR7210120002",
        "srtnCd": "A210120",
        "itmsNm": "\ube45\ud150\uce20",
        "trd_dd": "2014-12-30",
        "trdcnt1": "0",
        "trdcnt2": "0",
        "trdcnt3": "0",
        "trdcnt4": "0",
        "trdcnt5": "0",
        "trdcnt6": "0",
        "trdcnt7": "0",
        "trdcnt8": "0",
        "trdcnt9": "0",
        "trdcnt10": "0",
        "trdcnt11": "0",
        "trdcnt_tot": "0",
        "current_datetime": "2024-07-24 20:28:01.547299"
    },
    {
        "isinCd": "KR7210120002",
        "srtnCd": "A210120",
        "itmsNm": "\ube45\ud150\uce20",
        "trd_dd": "2014-12-29",
        "trdcnt1": "0",
        "trdcnt2": "0",
        "trdcnt3": "0",
        "trdcnt4": "0",
        "trdcnt5": "0",
        "trdcnt6": "0",
        "trdcnt7": "0",
        "trdcnt8": "0",
        "trdcnt9": "0",
        "trdcnt10": "0",
        "trdcnt11": "0",
        "trdcnt_tot": "0",
        "current_datetime": "2024-07-24 20:28:01.571216"
    },
    {
        "isinCd": "KR7210120002",
        "srtnCd": "A210120",
        "itmsNm": "\ube45\ud150\uce20",
        "trd_dd": "2014-12-26",
        "trdcnt1": "0",
        "trdcnt2": "0",
        "trdcnt3": "0",
        "trdcnt4": "0",
        "trdcnt5": "0",
        "trdcnt6": "0",
        "trdcnt7": "0",
        "trdcnt8": "0",
        "trdcnt9": "0",
        "trdcnt10": "0",
        "trdcnt11": "0",
        "trdcnt_tot": "0",
        "current_datetime": "2024-07-24 20:28:01.597780"
    },
    {
        "isinCd": "KR7210120002",
        "srtnCd": "A210120",
        "itmsNm": "\ube45\ud150\uce20",
        "trd_dd": "2014-12-24",
        "trdcnt1": "0",
        "trdcnt2": "0",
        "trdcnt3": "0",
        "trdcnt4": "0",
        "trdcnt5": "0",
        "trdcnt6": "0",
        "trdcnt7": "0",
        "trdcnt8": "0",
        "trdcnt9": "0",
        "trdcnt10": "0",
        "trdcnt11": "0",
        "trdcnt_tot": "0",
        "current_datetime": "2024-07-24 20:28:01.627458"
    },
    {
        "isinCd": "KR7210120002",
        "srtnCd": "A210120",
        "itmsNm": "\ube45\ud150\uce20",
        "trd_dd": "2014-12-23",
        "trdcnt1": "0",
        "trdcnt2": "0",
        "trdcnt3": "0",
        "trdcnt4": "0",
        "trdcnt5": "0",
        "trdcnt6": "0",
        "trdcnt7": "0",
        "trdcnt8": "0",
        "trdcnt9": "0",
        "trdcnt10": "0",
        "trdcnt11": "0",
        "trdcnt_tot": "0",
        "current_datetime": "2024-07-24 20:28:01.650754"
    },
    {
        "isinCd": "KR7210120002",
        "srtnCd": "A210120",
        "itmsNm": "\ube45\ud150\uce20",
        "trd_dd": "2014-12-22",
        "trdcnt1": "0",
        "trdcnt2": "0",
        "trdcnt3": "0",
        "trdcnt4": "0",
        "trdcnt5": "0",
        "trdcnt6": "0",
        "trdcnt7": "0",
        "trdcnt8": "0",
        "trdcnt9": "0",
        "trdcnt10": "0",
        "trdcnt11": "0",
        "trdcnt_tot": "0",
        "current_datetime": "2024-07-24 20:28:01.674248"
    },
    {
        "isinCd": "KR7210120002",
        "srtnCd": "A210120",
        "itmsNm": "\ube45\ud150\uce20",
        "trd_dd": "2014-12-19",
        "trdcnt1": "0",
        "trdcnt2": "0",
        "trdcnt3": "0",
        "trdcnt4": "0",
        "trdcnt5": "0",
        "trdcnt6": "0",
        "trdcnt7": "0",
        "trdcnt8": "0",
        "trdcnt9": "0",
        "trdcnt10": "0",
        "trdcnt11": "0",
        "trdcnt_tot": "0",
        "current_datetime": "2024-07-24 20:28:01.684558"
    },
    {
        "isinCd": "KR7210120002",
        "srtnCd": "A210120",
        "itmsNm": "\ube45\ud150\uce20",
        "trd_dd": "2014-12-18",
        "trdcnt1": "0",
        "trdcnt2": "0",
        "trdcnt3": "0",
        "trdcnt4": "0",
        "trdcnt5": "0",
        "trdcnt6": "0",
        "trdcnt7": "0",
        "trdcnt8": "0",
        "trdcnt9": "0",
        "trdcnt10": "0",
        "trdcnt11": "0",
        "trdcnt_tot": "0",
        "current_datetime": "2024-07-24 20:28:01.697860"
    },
    {
        "isinCd": "KR7210120002",
        "srtnCd": "A210120",
        "itmsNm": "\ube45\ud150\uce20",
        "trd_dd": "2014-12-17",
        "trdcnt1": "0",
        "trdcnt2": "0",
        "trdcnt3": "0",
        "trdcnt4": "0",
        "trdcnt5": "0",
        "trdcnt6": "0",
        "trdcnt7": "0",
        "trdcnt8": "0",
        "trdcnt9": "0",
        "trdcnt10": "0",
        "trdcnt11": "0",
        "trdcnt_tot": "0",
        "current_datetime": "2024-07-24 20:28:01.718129"
    },
    {
        "isinCd": "KR7210120002",
        "srtnCd": "A210120",
        "itmsNm": "\ube45\ud150\uce20",
        "trd_dd": "2014-12-16",
        "trdcnt1": "0",
        "trdcnt2": "0",
        "trdcnt3": "0",
        "trdcnt4": "0",
        "trdcnt5": "0",
        "trdcnt6": "0",
        "trdcnt7": "0",
        "trdcnt8": "0",
        "trdcnt9": "0",
        "trdcnt10": "0",
        "trdcnt11": "0",
        "trdcnt_tot": "0",
        "current_datetime": "2024-07-24 20:28:01.734410"
    },
    {
        "isinCd": "KR7210120002",
        "srtnCd": "A210120",
        "itmsNm": "\ube45\ud150\uce20",
        "trd_dd": "2015-01-02",
        "trdcnt1": "0",
        "trdcnt2": "0",
        "trdcnt3": "0",
        "trdcnt4": "0",
        "trdcnt5": "0",
        "trdcnt6": "0",
        "trdcnt7": "0",
        "trdcnt8": "0",
        "trdcnt9": "0",
        "trdcnt10": "0",
        "trdcnt11": "0",
        "trdcnt_tot": "0",
        "current_datetime": "2024-07-25 16:23:17.424592"
    },
    {
        "isinCd": "KR7210120002",
        "srtnCd": "A210120",
        "itmsNm": "\ube45\ud150\uce20",
        "trd_dd": "2014-12-30",
        "trdcnt1": "0",
        "trdcnt2": "0",
        "trdcnt3": "0",
        "trdcnt4": "0",
        "trdcnt5": "0",
        "trdcnt6": "0",
        "trdcnt7": "0",
        "trdcnt8": "0",
        "trdcnt9": "0",
        "trdcnt10": "0",
        "trdcnt11": "0",
        "trdcnt_tot": "0",
        "current_datetime": "2024-07-25 16:23:17.500667"
    },
    {
        "isinCd": "KR7210120002",
        "srtnCd": "A210120",
        "itmsNm": "\ube45\ud150\uce20",
        "trd_dd": "2014-12-29",
        "trdcnt1": "0",
        "trdcnt2": "0",
        "trdcnt3": "0",
        "trdcnt4": "0",
        "trdcnt5": "0",
        "trdcnt6": "0",
        "trdcnt7": "0",
        "trdcnt8": "0",
        "trdcnt9": "0",
        "trdcnt10": "0",
        "trdcnt11": "0",
        "trdcnt_tot": "0",
        "current_datetime": "2024-07-25 16:23:17.533466"
    },
    {
        "isinCd": "KR7210120002",
        "srtnCd": "A210120",
        "itmsNm": "\ube45\ud150\uce20",
        "trd_dd": "2014-12-26",
        "trdcnt1": "0",
        "trdcnt2": "0",
        "trdcnt3": "0",
        "trdcnt4": "0",
        "trdcnt5": "0",
        "trdcnt6": "0",
        "trdcnt7": "0",
        "trdcnt8": "0",
        "trdcnt9": "0",
        "trdcnt10": "0",
        "trdcnt11": "0",
        "trdcnt_tot": "0",
        "current_datetime": "2024-07-25 16:23:17.553925"
    },
    {
        "isinCd": "KR7210120002",
        "srtnCd": "A210120",
        "itmsNm": "\ube45\ud150\uce20",
        "trd_dd": "2014-12-24",
        "trdcnt1": "0",
        "trdcnt2": "0",
        "trdcnt3": "0",
        "trdcnt4": "0",
        "trdcnt5": "0",
        "trdcnt6": "0",
        "trdcnt7": "0",
        "trdcnt8": "0",
        "trdcnt9": "0",
        "trdcnt10": "0",
        "trdcnt11": "0",
        "trdcnt_tot": "0",
        "current_datetime": "2024-07-25 16:23:17.655862"
    },
    {
        "isinCd": "KR7210120002",
        "srtnCd": "A210120",
        "itmsNm": "\ube45\ud150\uce20",
        "trd_dd": "2014-12-23",
        "trdcnt1": "0",
        "trdcnt2": "0",
        "trdcnt3": "0",
        "trdcnt4": "0",
        "trdcnt5": "0",
        "trdcnt6": "0",
        "trdcnt7": "0",
        "trdcnt8": "0",
        "trdcnt9": "0",
        "trdcnt10": "0",
        "trdcnt11": "0",
        "trdcnt_tot": "0",
        "current_datetime": "2024-07-25 16:23:17.906933"
    },
    {
        "isinCd": "KR7210120002",
        "srtnCd": "A210120",
        "itmsNm": "\ube45\ud150\uce20",
        "trd_dd": "2014-12-22",
        "trdcnt1": "0",
        "trdcnt2": "0",
        "trdcnt3": "0",
        "trdcnt4": "0",
        "trdcnt5": "0",
        "trdcnt6": "0",
        "trdcnt7": "0",
        "trdcnt8": "0",
        "trdcnt9": "0",
        "trdcnt10": "0",
        "trdcnt11": "0",
        "trdcnt_tot": "0",
        "current_datetime": "2024-07-25 16:23:18.028558"
    },
    {
        "isinCd": "KR7210120002",
        "srtnCd": "A210120",
        "itmsNm": "\ube45\ud150\uce20",
        "trd_dd": "2014-12-19",
        "trdcnt1": "0",
        "trdcnt2": "0",
        "trdcnt3": "0",
        "trdcnt4": "0",
        "trdcnt5": "0",
        "trdcnt6": "0",
        "trdcnt7": "0",
        "trdcnt8": "0",
        "trdcnt9": "0",
        "trdcnt10": "0",
        "trdcnt11": "0",
        "trdcnt_tot": "0",
        "current_datetime": "2024-07-25 16:23:18.114006"
    },
    {
        "isinCd": "KR7210120002",
        "srtnCd": "A210120",
        "itmsNm": "\ube45\ud150\uce20",
        "trd_dd": "2014-12-18",
        "trdcnt1": "0",
        "trdcnt2": "0",
        "trdcnt3": "0",
        "trdcnt4": "0",
        "trdcnt5": "0",
        "trdcnt6": "0",
        "trdcnt7": "0",
        "trdcnt8": "0",
        "trdcnt9": "0",
        "trdcnt10": "0",
        "trdcnt11": "0",
        "trdcnt_tot": "0",
        "current_datetime": "2024-07-25 16:23:18.240637"
    },
    {
        "isinCd": "KR7210120002",
        "srtnCd": "A210120",
        "itmsNm": "\ube45\ud150\uce20",
        "trd_dd": "2014-12-17",
        "trdcnt1": "0",
        "trdcnt2": "0",
        "trdcnt3": "0",
        "trdcnt4": "0",
        "trdcnt5": "0",
        "trdcnt6": "0",
        "trdcnt7": "0",
        "trdcnt8": "0",
        "trdcnt9": "0",
        "trdcnt10": "0",
        "trdcnt11": "0",
        "trdcnt_tot": "0",
        "current_datetime": "2024-07-25 16:23:18.390014"
    },
    {
        "isinCd": "KR7210120002",
        "srtnCd": "A210120",
        "itmsNm": "\ube45\ud150\uce20",
        "trd_dd": "2014-12-16",
        "trdcnt1": "0",
        "trdcnt2": "0",
        "trdcnt3": "0",
        "trdcnt4": "0",
        "trdcnt5": "0",
        "trdcnt6": "0",
        "trdcnt7": "0",
        "trdcnt8": "0",
        "trdcnt9": "0",
        "trdcnt10": "0",
        "trdcnt11": "0",
        "trdcnt_tot": "0",
        "current_datetime": "2024-07-25 16:23:18.427641"
    }
]