[
    {
        "isinCd": "KR7419120001",
        "srtnCd": "A419120",
        "itmsNm": "\uc0b0\ub3cc",
        "trd_dd": "2023-01-05",
        "trdcnt1": "1,380",
        "trdcnt2": "0",
        "trdcnt3": "-61",
        "trdcnt4": "1,000",
        "trdcnt5": "0",
        "trdcnt6": "0",
        "trdcnt7": "0",
        "trdcnt8": "-1",
        "trdcnt9": "-5,736",
        "trdcnt10": "3,257",
        "trdcnt11": "161",
        "trdcnt_tot": "0",
        "current_datetime": "2024-07-24 21:00:18.459461"
    },
    {
        "isinCd": "KR7419120001",
        "srtnCd": "A419120",
        "itmsNm": "\uc0b0\ub3cc",
        "trd_dd": "2023-01-04",
        "trdcnt1": "4,971",
        "trdcnt2": "0",
        "trdcnt3": "0",
        "trdcnt4": "4,000",
        "trdcnt5": "0",
        "trdcnt6": "0",
        "trdcnt7": "0",
        "trdcnt8": "-6",
        "trdcnt9": "-13,790",
        "trdcnt10": "4,275",
        "trdcnt11": "550",
        "trdcnt_tot": "0",
        "current_datetime": "2024-07-24 21:00:18.482846"
    },
    {
        "isinCd": "KR7419120001",
        "srtnCd": "A419120",
        "itmsNm": "\uc0b0\ub3cc",
        "trd_dd": "2023-01-03",
        "trdcnt1": "0",
        "trdcnt2": "0",
        "trdcnt3": "219",
        "trdcnt4": "191",
        "trdcnt5": "0",
        "trdcnt6": "0",
        "trdcnt7": "0",
        "trdcnt8": "17",
        "trdcnt9": "-987",
        "trdcnt10": "717",
        "trdcnt11": "-157",
        "trdcnt_tot": "0",
        "current_datetime": "2024-07-24 21:00:18.500503"
    },
    {
        "isinCd": "KR7419120001",
        "srtnCd": "A419120",
        "itmsNm": "\uc0b0\ub3cc",
        "trd_dd": "2023-01-02",
        "trdcnt1": "0",
        "trdcnt2": "0",
        "trdcnt3": "687",
        "trdcnt4": "139",
        "trdcnt5": "0",
        "trdcnt6": "-1",
        "trdcnt7": "0",
        "trdcnt8": "0",
        "trdcnt9": "-2,665",
        "trdcnt10": "1,696",
        "trdcnt11": "144",
        "trdcnt_tot": "0",
        "current_datetime": "2024-07-24 21:00:18.555720"
    },
    {
        "isinCd": "KR7419120001",
        "srtnCd": "A419120",
        "itmsNm": "\uc0b0\ub3cc",
        "trd_dd": "2022-12-29",
        "trdcnt1": "0",
        "trdcnt2": "0",
        "trdcnt3": "572",
        "trdcnt4": "0",
        "trdcnt5": "0",
        "trdcnt6": "0",
        "trdcnt7": "0",
        "trdcnt8": "300",
        "trdcnt9": "2,902",
        "trdcnt10": "-3,881",
        "trdcnt11": "107",
        "trdcnt_tot": "0",
        "current_datetime": "2024-07-24 21:00:18.583088"
    },
    {
        "isinCd": "KR7419120001",
        "srtnCd": "A419120",
        "itmsNm": "\uc0b0\ub3cc",
        "trd_dd": "2022-12-28",
        "trdcnt1": "0",
        "trdcnt2": "0",
        "trdcnt3": "500",
        "trdcnt4": "0",
        "trdcnt5": "0",
        "trdcnt6": "0",
        "trdcnt7": "0",
        "trdcnt8": "0",
        "trdcnt9": "2,206",
        "trdcnt10": "-2,735",
        "trdcnt11": "29",
        "trdcnt_tot": "0",
        "current_datetime": "2024-07-24 21:00:18.608820"
    },
    {
        "isinCd": "KR7419120001",
        "srtnCd": "A419120",
        "itmsNm": "\uc0b0\ub3cc",
        "trd_dd": "2022-12-27",
        "trdcnt1": "0",
        "trdcnt2": "0",
        "trdcnt3": "34",
        "trdcnt4": "608",
        "trdcnt5": "0",
        "trdcnt6": "0",
        "trdcnt7": "0",
        "trdcnt8": "-303",
        "trdcnt9": "-683",
        "trdcnt10": "382",
        "trdcnt11": "-38",
        "trdcnt_tot": "0",
        "current_datetime": "2024-07-24 21:00:18.644774"
    },
    {
        "isinCd": "KR7419120001",
        "srtnCd": "A419120",
        "itmsNm": "\uc0b0\ub3cc",
        "trd_dd": "2022-12-26",
        "trdcnt1": "0",
        "trdcnt2": "0",
        "trdcnt3": "-839",
        "trdcnt4": "0",
        "trdcnt5": "0",
        "trdcnt6": "1",
        "trdcnt7": "0",
        "trdcnt8": "300",
        "trdcnt9": "2,359",
        "trdcnt10": "-1,833",
        "trdcnt11": "12",
        "trdcnt_tot": "0",
        "current_datetime": "2024-07-24 21:00:18.660937"
    },
    {
        "isinCd": "KR7419120001",
        "srtnCd": "A419120",
        "itmsNm": "\uc0b0\ub3cc",
        "trd_dd": "2022-12-23",
        "trdcnt1": "201",
        "trdcnt2": "0",
        "trdcnt3": "-3,522",
        "trdcnt4": "-6,166",
        "trdcnt5": "0",
        "trdcnt6": "0",
        "trdcnt7": "0",
        "trdcnt8": "106",
        "trdcnt9": "8,048",
        "trdcnt10": "1,773",
        "trdcnt11": "-440",
        "trdcnt_tot": "0",
        "current_datetime": "2024-07-24 21:00:18.686696"
    },
    {
        "isinCd": "KR7419120001",
        "srtnCd": "A419120",
        "itmsNm": "\uc0b0\ub3cc",
        "trd_dd": "2022-12-22",
        "trdcnt1": "0",
        "trdcnt2": "0",
        "trdcnt3": "-37",
        "trdcnt4": "0",
        "trdcnt5": "0",
        "trdcnt6": "-6,389",
        "trdcnt7": "0",
        "trdcnt8": "0",
        "trdcnt9": "7,107",
        "trdcnt10": "-852",
        "trdcnt11": "171",
        "trdcnt_tot": "0",
        "current_datetime": "2024-07-24 21:00:18.702055"
    },
    {
        "isinCd": "KR7419120001",
        "srtnCd": "A419120",
        "itmsNm": "\uc0b0\ub3cc",
        "trd_dd": "2022-12-21",
        "trdcnt1": "0",
        "trdcnt2": "0",
        "trdcnt3": "1,412",
        "trdcnt4": "-19,135",
        "trdcnt5": "0",
        "trdcnt6": "-1,600",
        "trdcnt7": "0",
        "trdcnt8": "0",
        "trdcnt9": "31,095",
        "trdcnt10": "-11,341",
        "trdcnt11": "-431",
        "trdcnt_tot": "0",
        "current_datetime": "2024-07-24 21:00:18.721681"
    },
    {
        "isinCd": "KR7419120001",
        "srtnCd": "A419120",
        "itmsNm": "\uc0b0\ub3cc",
        "trd_dd": "2022-12-20",
        "trdcnt1": "0",
        "trdcnt2": "0",
        "trdcnt3": "23",
        "trdcnt4": "3,500",
        "trdcnt5": "0",
        "trdcnt6": "-2,000",
        "trdcnt7": "0",
        "trdcnt8": "0",
        "trdcnt9": "11,523",
        "trdcnt10": "-13,103",
        "trdcnt11": "57",
        "trdcnt_tot": "0",
        "current_datetime": "2024-07-24 21:00:18.735893"
    },
    {
        "isinCd": "KR7419120001",
        "srtnCd": "A419120",
        "itmsNm": "\uc0b0\ub3cc",
        "trd_dd": "2022-12-19",
        "trdcnt1": "-295",
        "trdcnt2": "0",
        "trdcnt3": "2,808",
        "trdcnt4": "3,500",
        "trdcnt5": "0",
        "trdcnt6": "-3,600",
        "trdcnt7": "0",
        "trdcnt8": "1",
        "trdcnt9": "-513",
        "trdcnt10": "-1,901",
        "trdcnt11": "0",
        "trdcnt_tot": "0",
        "current_datetime": "2024-07-24 21:00:18.749659"
    },
    {
        "isinCd": "KR7419120001",
        "srtnCd": "A419120",
        "itmsNm": "\uc0b0\ub3cc",
        "trd_dd": "2022-12-16",
        "trdcnt1": "0",
        "trdcnt2": "0",
        "trdcnt3": "2,606",
        "trdcnt4": "0",
        "trdcnt5": "0",
        "trdcnt6": "-2,000",
        "trdcnt7": "0",
        "trdcnt8": "0",
        "trdcnt9": "3,178",
        "trdcnt10": "-3,711",
        "trdcnt11": "-73",
        "trdcnt_tot": "0",
        "current_datetime": "2024-07-24 21:00:18.769211"
    },
    {
        "isinCd": "KR7419120001",
        "srtnCd": "A419120",
        "itmsNm": "\uc0b0\ub3cc",
        "trd_dd": "2022-12-15",
        "trdcnt1": "-500",
        "trdcnt2": "0",
        "trdcnt3": "3,104",
        "trdcnt4": "-387",
        "trdcnt5": "0",
        "trdcnt6": "-3,600",
        "trdcnt7": "0",
        "trdcnt8": "0",
        "trdcnt9": "-7,129",
        "trdcnt10": "8,754",
        "trdcnt11": "-242",
        "trdcnt_tot": "0",
        "current_datetime": "2024-07-24 21:00:18.782091"
    },
    {
        "isinCd": "KR7419120001",
        "srtnCd": "A419120",
        "itmsNm": "\uc0b0\ub3cc",
        "trd_dd": "2022-12-14",
        "trdcnt1": "0",
        "trdcnt2": "0",
        "trdcnt3": "763",
        "trdcnt4": "0",
        "trdcnt5": "0",
        "trdcnt6": "-5,600",
        "trdcnt7": "0",
        "trdcnt8": "0",
        "trdcnt9": "-251",
        "trdcnt10": "5,284",
        "trdcnt11": "-196",
        "trdcnt_tot": "0",
        "current_datetime": "2024-07-24 21:00:18.808739"
    },
    {
        "isinCd": "KR7419120001",
        "srtnCd": "A419120",
        "itmsNm": "\uc0b0\ub3cc",
        "trd_dd": "2022-12-13",
        "trdcnt1": "0",
        "trdcnt2": "0",
        "trdcnt3": "2,860",
        "trdcnt4": "-574",
        "trdcnt5": "0",
        "trdcnt6": "-4,000",
        "trdcnt7": "0",
        "trdcnt8": "0",
        "trdcnt9": "956",
        "trdcnt10": "771",
        "trdcnt11": "-13",
        "trdcnt_tot": "0",
        "current_datetime": "2024-07-24 21:00:18.829324"
    },
    {
        "isinCd": "KR7419120001",
        "srtnCd": "A419120",
        "itmsNm": "\uc0b0\ub3cc",
        "trd_dd": "2022-12-12",
        "trdcnt1": "0",
        "trdcnt2": "0",
        "trdcnt3": "0",
        "trdcnt4": "0",
        "trdcnt5": "0",
        "trdcnt6": "-6,000",
        "trdcnt7": "0",
        "trdcnt8": "0",
        "trdcnt9": "-3,585",
        "trdcnt10": "9,583",
        "trdcnt11": "2",
        "trdcnt_tot": "0",
        "current_datetime": "2024-07-24 21:00:18.839499"
    },
    {
        "isinCd": "KR7419120001",
        "srtnCd": "A419120",
        "itmsNm": "\uc0b0\ub3cc",
        "trd_dd": "2022-12-09",
        "trdcnt1": "226",
        "trdcnt2": "0",
        "trdcnt3": "0",
        "trdcnt4": "0",
        "trdcnt5": "0",
        "trdcnt6": "-1,200",
        "trdcnt7": "0",
        "trdcnt8": "0",
        "trdcnt9": "2,126",
        "trdcnt10": "-1,152",
        "trdcnt11": "0",
        "trdcnt_tot": "0",
        "current_datetime": "2024-07-24 21:00:18.864020"
    },
    {
        "isinCd": "KR7419120001",
        "srtnCd": "A419120",
        "itmsNm": "\uc0b0\ub3cc",
        "trd_dd": "2022-12-08",
        "trdcnt1": "1",
        "trdcnt2": "0",
        "trdcnt3": "500",
        "trdcnt4": "2,278",
        "trdcnt5": "0",
        "trdcnt6": "-14,400",
        "trdcnt7": "0",
        "trdcnt8": "1,089",
        "trdcnt9": "5,795",
        "trdcnt10": "4,737",
        "trdcnt11": "0",
        "trdcnt_tot": "0",
        "current_datetime": "2024-07-24 21:00:18.885031"
    },
    {
        "isinCd": "KR7419120001",
        "srtnCd": "A419120",
        "itmsNm": "\uc0b0\ub3cc",
        "trd_dd": "2022-12-07",
        "trdcnt1": "0",
        "trdcnt2": "0",
        "trdcnt3": "712",
        "trdcnt4": "123",
        "trdcnt5": "0",
        "trdcnt6": "-6,200",
        "trdcnt7": "0",
        "trdcnt8": "0",
        "trdcnt9": "15,224",
        "trdcnt10": "-9,883",
        "trdcnt11": "24",
        "trdcnt_tot": "0",
        "current_datetime": "2024-07-24 21:00:18.902995"
    },
    {
        "isinCd": "KR7419120001",
        "srtnCd": "A419120",
        "itmsNm": "\uc0b0\ub3cc",
        "trd_dd": "2022-12-06",
        "trdcnt1": "0",
        "trdcnt2": "0",
        "trdcnt3": "0",
        "trdcnt4": "0",
        "trdcnt5": "0",
        "trdcnt6": "-9,201",
        "trdcnt7": "0",
        "trdcnt8": "0",
        "trdcnt9": "10,183",
        "trdcnt10": "-1,088",
        "trdcnt11": "106",
        "trdcnt_tot": "0",
        "current_datetime": "2024-07-24 21:00:18.923829"
    },
    {
        "isinCd": "KR7419120001",
        "srtnCd": "A419120",
        "itmsNm": "\uc0b0\ub3cc",
        "trd_dd": "2022-12-05",
        "trdcnt1": "102",
        "trdcnt2": "0",
        "trdcnt3": "0",
        "trdcnt4": "0",
        "trdcnt5": "0",
        "trdcnt6": "-4,400",
        "trdcnt7": "0",
        "trdcnt8": "0",
        "trdcnt9": "5,013",
        "trdcnt10": "-725",
        "trdcnt11": "10",
        "trdcnt_tot": "0",
        "current_datetime": "2024-07-24 21:00:18.957074"
    },
    {
        "isinCd": "KR7419120001",
        "srtnCd": "A419120",
        "itmsNm": "\uc0b0\ub3cc",
        "trd_dd": "2022-12-02",
        "trdcnt1": "1",
        "trdcnt2": "0",
        "trdcnt3": "0",
        "trdcnt4": "21",
        "trdcnt5": "0",
        "trdcnt6": "-10,799",
        "trdcnt7": "0",
        "trdcnt8": "0",
        "trdcnt9": "5,105",
        "trdcnt10": "4,813",
        "trdcnt11": "859",
        "trdcnt_tot": "0",
        "current_datetime": "2024-07-24 21:00:18.989487"
    },
    {
        "isinCd": "KR7419120001",
        "srtnCd": "A419120",
        "itmsNm": "\uc0b0\ub3cc",
        "trd_dd": "2022-12-01",
        "trdcnt1": "1,001",
        "trdcnt2": "0",
        "trdcnt3": "0",
        "trdcnt4": "0",
        "trdcnt5": "0",
        "trdcnt6": "-12,000",
        "trdcnt7": "0",
        "trdcnt8": "0",
        "trdcnt9": "3,003",
        "trdcnt10": "7,652",
        "trdcnt11": "344",
        "trdcnt_tot": "0",
        "current_datetime": "2024-07-24 21:00:19.007209"
    },
    {
        "isinCd": "KR7419120001",
        "srtnCd": "A419120",
        "itmsNm": "\uc0b0\ub3cc",
        "trd_dd": "2022-11-30",
        "trdcnt1": "5",
        "trdcnt2": "0",
        "trdcnt3": "0",
        "trdcnt4": "0",
        "trdcnt5": "0",
        "trdcnt6": "-4,999",
        "trdcnt7": "0",
        "trdcnt8": "0",
        "trdcnt9": "1,333",
        "trdcnt10": "3,155",
        "trdcnt11": "506",
        "trdcnt_tot": "0",
        "current_datetime": "2024-07-24 21:00:19.024933"
    },
    {
        "isinCd": "KR7419120001",
        "srtnCd": "A419120",
        "itmsNm": "\uc0b0\ub3cc",
        "trd_dd": "2022-11-29",
        "trdcnt1": "372",
        "trdcnt2": "0",
        "trdcnt3": "-3,026",
        "trdcnt4": "213",
        "trdcnt5": "0",
        "trdcnt6": "-14,794",
        "trdcnt7": "0",
        "trdcnt8": "200",
        "trdcnt9": "13,371",
        "trdcnt10": "3,529",
        "trdcnt11": "135",
        "trdcnt_tot": "0",
        "current_datetime": "2024-07-24 21:00:19.076916"
    },
    {
        "isinCd": "KR7419120001",
        "srtnCd": "A419120",
        "itmsNm": "\uc0b0\ub3cc",
        "trd_dd": "2022-11-28",
        "trdcnt1": "200",
        "trdcnt2": "0",
        "trdcnt3": "0",
        "trdcnt4": "0",
        "trdcnt5": "0",
        "trdcnt6": "-21,206",
        "trdcnt7": "0",
        "trdcnt8": "400",
        "trdcnt9": "23,864",
        "trdcnt10": "-3,615",
        "trdcnt11": "357",
        "trdcnt_tot": "0",
        "current_datetime": "2024-07-24 21:00:19.109213"
    },
    {
        "isinCd": "KR7419120001",
        "srtnCd": "A419120",
        "itmsNm": "\uc0b0\ub3cc",
        "trd_dd": "2022-11-25",
        "trdcnt1": "-70",
        "trdcnt2": "0",
        "trdcnt3": "1,951",
        "trdcnt4": "0",
        "trdcnt5": "0",
        "trdcnt6": "0",
        "trdcnt7": "0",
        "trdcnt8": "0",
        "trdcnt9": "9,441",
        "trdcnt10": "-8,400",
        "trdcnt11": "-2,922",
        "trdcnt_tot": "0",
        "current_datetime": "2024-07-24 21:00:19.154213"
    },
    {
        "isinCd": "KR7419120001",
        "srtnCd": "A419120",
        "itmsNm": "\uc0b0\ub3cc",
        "trd_dd": "2022-11-24",
        "trdcnt1": "-3,930",
        "trdcnt2": "0",
        "trdcnt3": "-781",
        "trdcnt4": "514",
        "trdcnt5": "0",
        "trdcnt6": "0",
        "trdcnt7": "0",
        "trdcnt8": "-658",
        "trdcnt9": "1,188",
        "trdcnt10": "3,537",
        "trdcnt11": "130",
        "trdcnt_tot": "0",
        "current_datetime": "2024-07-24 21:00:19.193801"
    },
    {
        "isinCd": "KR7419120001",
        "srtnCd": "A419120",
        "itmsNm": "\uc0b0\ub3cc",
        "trd_dd": "2022-11-23",
        "trdcnt1": "0",
        "trdcnt2": "0",
        "trdcnt3": "0",
        "trdcnt4": "0",
        "trdcnt5": "0",
        "trdcnt6": "0",
        "trdcnt7": "0",
        "trdcnt8": "-582",
        "trdcnt9": "-1,235",
        "trdcnt10": "956",
        "trdcnt11": "861",
        "trdcnt_tot": "0",
        "current_datetime": "2024-07-24 21:00:19.241404"
    },
    {
        "isinCd": "KR7419120001",
        "srtnCd": "A419120",
        "itmsNm": "\uc0b0\ub3cc",
        "trd_dd": "2022-11-22",
        "trdcnt1": "-7,689",
        "trdcnt2": "0",
        "trdcnt3": "0",
        "trdcnt4": "0",
        "trdcnt5": "0",
        "trdcnt6": "0",
        "trdcnt7": "0",
        "trdcnt8": "-1,362",
        "trdcnt9": "10,125",
        "trdcnt10": "-1,096",
        "trdcnt11": "22",
        "trdcnt_tot": "0",
        "current_datetime": "2024-07-24 21:00:19.281470"
    },
    {
        "isinCd": "KR7419120001",
        "srtnCd": "A419120",
        "itmsNm": "\uc0b0\ub3cc",
        "trd_dd": "2022-11-21",
        "trdcnt1": "0",
        "trdcnt2": "0",
        "trdcnt3": "0",
        "trdcnt4": "-12,255",
        "trdcnt5": "0",
        "trdcnt6": "0",
        "trdcnt7": "0",
        "trdcnt8": "138",
        "trdcnt9": "11,902",
        "trdcnt10": "-922",
        "trdcnt11": "1,137",
        "trdcnt_tot": "0",
        "current_datetime": "2024-07-24 21:00:19.310256"
    },
    {
        "isinCd": "KR7419120001",
        "srtnCd": "A419120",
        "itmsNm": "\uc0b0\ub3cc",
        "trd_dd": "2022-11-18",
        "trdcnt1": "200",
        "trdcnt2": "0",
        "trdcnt3": "0",
        "trdcnt4": "0",
        "trdcnt5": "0",
        "trdcnt6": "0",
        "trdcnt7": "0",
        "trdcnt8": "2,100",
        "trdcnt9": "-3,193",
        "trdcnt10": "-110",
        "trdcnt11": "1,003",
        "trdcnt_tot": "0",
        "current_datetime": "2024-07-24 21:00:19.350536"
    },
    {
        "isinCd": "KR7419120001",
        "srtnCd": "A419120",
        "itmsNm": "\uc0b0\ub3cc",
        "trd_dd": "2022-11-17",
        "trdcnt1": "0",
        "trdcnt2": "0",
        "trdcnt3": "0",
        "trdcnt4": "0",
        "trdcnt5": "0",
        "trdcnt6": "0",
        "trdcnt7": "0",
        "trdcnt8": "0",
        "trdcnt9": "919",
        "trdcnt10": "-640",
        "trdcnt11": "-279",
        "trdcnt_tot": "0",
        "current_datetime": "2024-07-24 21:00:19.387966"
    },
    {
        "isinCd": "KR7419120001",
        "srtnCd": "A419120",
        "itmsNm": "\uc0b0\ub3cc",
        "trd_dd": "2022-11-16",
        "trdcnt1": "0",
        "trdcnt2": "0",
        "trdcnt3": "0",
        "trdcnt4": "0",
        "trdcnt5": "0",
        "trdcnt6": "0",
        "trdcnt7": "0",
        "trdcnt8": "0",
        "trdcnt9": "66",
        "trdcnt10": "102",
        "trdcnt11": "-168",
        "trdcnt_tot": "0",
        "current_datetime": "2024-07-24 21:00:19.413510"
    },
    {
        "isinCd": "KR7419120001",
        "srtnCd": "A419120",
        "itmsNm": "\uc0b0\ub3cc",
        "trd_dd": "2022-11-15",
        "trdcnt1": "0",
        "trdcnt2": "0",
        "trdcnt3": "0",
        "trdcnt4": "1,500",
        "trdcnt5": "0",
        "trdcnt6": "1",
        "trdcnt7": "0",
        "trdcnt8": "0",
        "trdcnt9": "-2,203",
        "trdcnt10": "-287",
        "trdcnt11": "989",
        "trdcnt_tot": "0",
        "current_datetime": "2024-07-24 21:00:19.434380"
    },
    {
        "isinCd": "KR7419120001",
        "srtnCd": "A419120",
        "itmsNm": "\uc0b0\ub3cc",
        "trd_dd": "2022-11-14",
        "trdcnt1": "0",
        "trdcnt2": "0",
        "trdcnt3": "2,464",
        "trdcnt4": "0",
        "trdcnt5": "0",
        "trdcnt6": "1",
        "trdcnt7": "0",
        "trdcnt8": "-300",
        "trdcnt9": "2,933",
        "trdcnt10": "-4,738",
        "trdcnt11": "-360",
        "trdcnt_tot": "0",
        "current_datetime": "2024-07-24 21:00:19.459868"
    },
    {
        "isinCd": "KR7419120001",
        "srtnCd": "A419120",
        "itmsNm": "\uc0b0\ub3cc",
        "trd_dd": "2022-11-11",
        "trdcnt1": "0",
        "trdcnt2": "0",
        "trdcnt3": "0",
        "trdcnt4": "0",
        "trdcnt5": "0",
        "trdcnt6": "0",
        "trdcnt7": "0",
        "trdcnt8": "-1",
        "trdcnt9": "2,914",
        "trdcnt10": "-3,004",
        "trdcnt11": "91",
        "trdcnt_tot": "0",
        "current_datetime": "2024-07-24 21:00:19.481604"
    },
    {
        "isinCd": "KR7419120001",
        "srtnCd": "A419120",
        "itmsNm": "\uc0b0\ub3cc",
        "trd_dd": "2022-11-10",
        "trdcnt1": "585",
        "trdcnt2": "0",
        "trdcnt3": "1,169",
        "trdcnt4": "591",
        "trdcnt5": "0",
        "trdcnt6": "0",
        "trdcnt7": "0",
        "trdcnt8": "1",
        "trdcnt9": "-24,254",
        "trdcnt10": "20,775",
        "trdcnt11": "1,133",
        "trdcnt_tot": "0",
        "current_datetime": "2024-07-24 21:00:19.503478"
    },
    {
        "isinCd": "KR7419120001",
        "srtnCd": "A419120",
        "itmsNm": "\uc0b0\ub3cc",
        "trd_dd": "2022-11-09",
        "trdcnt1": "0",
        "trdcnt2": "0",
        "trdcnt3": "0",
        "trdcnt4": "0",
        "trdcnt5": "0",
        "trdcnt6": "0",
        "trdcnt7": "0",
        "trdcnt8": "0",
        "trdcnt9": "12,031",
        "trdcnt10": "-12,031",
        "trdcnt11": "0",
        "trdcnt_tot": "0",
        "current_datetime": "2024-07-24 21:00:19.555053"
    },
    {
        "isinCd": "KR7419120001",
        "srtnCd": "A419120",
        "itmsNm": "\uc0b0\ub3cc",
        "trd_dd": "2022-11-08",
        "trdcnt1": "0",
        "trdcnt2": "0",
        "trdcnt3": "0",
        "trdcnt4": "0",
        "trdcnt5": "0",
        "trdcnt6": "0",
        "trdcnt7": "0",
        "trdcnt8": "-2,438",
        "trdcnt9": "-9,125",
        "trdcnt10": "11,649",
        "trdcnt11": "-86",
        "trdcnt_tot": "0",
        "current_datetime": "2024-07-24 21:00:19.600520"
    },
    {
        "isinCd": "KR7419120001",
        "srtnCd": "A419120",
        "itmsNm": "\uc0b0\ub3cc",
        "trd_dd": "2022-11-07",
        "trdcnt1": "0",
        "trdcnt2": "0",
        "trdcnt3": "0",
        "trdcnt4": "0",
        "trdcnt5": "0",
        "trdcnt6": "0",
        "trdcnt7": "0",
        "trdcnt8": "0",
        "trdcnt9": "3,827",
        "trdcnt10": "-3,927",
        "trdcnt11": "100",
        "trdcnt_tot": "0",
        "current_datetime": "2024-07-24 21:00:19.617820"
    },
    {
        "isinCd": "KR7419120001",
        "srtnCd": "A419120",
        "itmsNm": "\uc0b0\ub3cc",
        "trd_dd": "2022-11-04",
        "trdcnt1": "6,000",
        "trdcnt2": "0",
        "trdcnt3": "16",
        "trdcnt4": "-296",
        "trdcnt5": "0",
        "trdcnt6": "0",
        "trdcnt7": "0",
        "trdcnt8": "922",
        "trdcnt9": "-2,571",
        "trdcnt10": "-3,198",
        "trdcnt11": "-873",
        "trdcnt_tot": "0",
        "current_datetime": "2024-07-24 21:00:19.650734"
    },
    {
        "isinCd": "KR7419120001",
        "srtnCd": "A419120",
        "itmsNm": "\uc0b0\ub3cc",
        "trd_dd": "2022-11-03",
        "trdcnt1": "-400",
        "trdcnt2": "0",
        "trdcnt3": "0",
        "trdcnt4": "0",
        "trdcnt5": "0",
        "trdcnt6": "0",
        "trdcnt7": "0",
        "trdcnt8": "-830",
        "trdcnt9": "2,961",
        "trdcnt10": "-1,617",
        "trdcnt11": "-114",
        "trdcnt_tot": "0",
        "current_datetime": "2024-07-24 21:00:19.671177"
    },
    {
        "isinCd": "KR7419120001",
        "srtnCd": "A419120",
        "itmsNm": "\uc0b0\ub3cc",
        "trd_dd": "2022-11-02",
        "trdcnt1": "-200",
        "trdcnt2": "0",
        "trdcnt3": "0",
        "trdcnt4": "1,995",
        "trdcnt5": "0",
        "trdcnt6": "0",
        "trdcnt7": "0",
        "trdcnt8": "-4",
        "trdcnt9": "-13,507",
        "trdcnt10": "11,255",
        "trdcnt11": "461",
        "trdcnt_tot": "0",
        "current_datetime": "2024-07-24 21:00:19.686895"
    },
    {
        "isinCd": "KR7419120001",
        "srtnCd": "A419120",
        "itmsNm": "\uc0b0\ub3cc",
        "trd_dd": "2022-11-01",
        "trdcnt1": "5,200",
        "trdcnt2": "0",
        "trdcnt3": "500",
        "trdcnt4": "554",
        "trdcnt5": "0",
        "trdcnt6": "0",
        "trdcnt7": "0",
        "trdcnt8": "2,905",
        "trdcnt9": "-4,972",
        "trdcnt10": "-4,620",
        "trdcnt11": "433",
        "trdcnt_tot": "0",
        "current_datetime": "2024-07-24 21:00:19.730929"
    },
    {
        "isinCd": "KR7419120001",
        "srtnCd": "A419120",
        "itmsNm": "\uc0b0\ub3cc",
        "trd_dd": "2022-10-31",
        "trdcnt1": "1,001",
        "trdcnt2": "0",
        "trdcnt3": "0",
        "trdcnt4": "-9,000",
        "trdcnt5": "0",
        "trdcnt6": "0",
        "trdcnt7": "0",
        "trdcnt8": "-257",
        "trdcnt9": "10,199",
        "trdcnt10": "-2,012",
        "trdcnt11": "69",
        "trdcnt_tot": "0",
        "current_datetime": "2024-07-24 21:00:19.752604"
    },
    {
        "isinCd": "KR7419120001",
        "srtnCd": "A419120",
        "itmsNm": "\uc0b0\ub3cc",
        "trd_dd": "2022-10-28",
        "trdcnt1": "192",
        "trdcnt2": "0",
        "trdcnt3": "3,984",
        "trdcnt4": "29",
        "trdcnt5": "0",
        "trdcnt6": "-852",
        "trdcnt7": "0",
        "trdcnt8": "165",
        "trdcnt9": "4,095",
        "trdcnt10": "-6,095",
        "trdcnt11": "-1,518",
        "trdcnt_tot": "0",
        "current_datetime": "2024-07-24 21:00:19.795282"
    },
    {
        "isinCd": "KR7419120001",
        "srtnCd": "A419120",
        "itmsNm": "\uc0b0\ub3cc",
        "trd_dd": "2022-10-27",
        "trdcnt1": "-35,922",
        "trdcnt2": "-999",
        "trdcnt3": "-101,377",
        "trdcnt4": "-275,814",
        "trdcnt5": "-666",
        "trdcnt6": "-16,577",
        "trdcnt7": "-2,562",
        "trdcnt8": "-15,530",
        "trdcnt9": "535,238",
        "trdcnt10": "-88,483",
        "trdcnt11": "2,692",
        "trdcnt_tot": "0",
        "current_datetime": "2024-07-24 21:00:19.823681"
    },
    {
        "isinCd": "KR7419120001",
        "srtnCd": "A419120",
        "itmsNm": "\uc0b0\ub3cc",
        "trd_dd": "2023-01-05",
        "trdcnt1": "1,380",
        "trdcnt2": "0",
        "trdcnt3": "-61",
        "trdcnt4": "1,000",
        "trdcnt5": "0",
        "trdcnt6": "0",
        "trdcnt7": "0",
        "trdcnt8": "-1",
        "trdcnt9": "-5,736",
        "trdcnt10": "3,257",
        "trdcnt11": "161",
        "trdcnt_tot": "0",
        "current_datetime": "2024-07-25 17:38:57.098140"
    },
    {
        "isinCd": "KR7419120001",
        "srtnCd": "A419120",
        "itmsNm": "\uc0b0\ub3cc",
        "trd_dd": "2023-01-04",
        "trdcnt1": "4,971",
        "trdcnt2": "0",
        "trdcnt3": "0",
        "trdcnt4": "4,000",
        "trdcnt5": "0",
        "trdcnt6": "0",
        "trdcnt7": "0",
        "trdcnt8": "-6",
        "trdcnt9": "-13,790",
        "trdcnt10": "4,275",
        "trdcnt11": "550",
        "trdcnt_tot": "0",
        "current_datetime": "2024-07-25 17:38:57.184615"
    },
    {
        "isinCd": "KR7419120001",
        "srtnCd": "A419120",
        "itmsNm": "\uc0b0\ub3cc",
        "trd_dd": "2023-01-03",
        "trdcnt1": "0",
        "trdcnt2": "0",
        "trdcnt3": "219",
        "trdcnt4": "191",
        "trdcnt5": "0",
        "trdcnt6": "0",
        "trdcnt7": "0",
        "trdcnt8": "17",
        "trdcnt9": "-987",
        "trdcnt10": "717",
        "trdcnt11": "-157",
        "trdcnt_tot": "0",
        "current_datetime": "2024-07-25 17:38:57.326176"
    },
    {
        "isinCd": "KR7419120001",
        "srtnCd": "A419120",
        "itmsNm": "\uc0b0\ub3cc",
        "trd_dd": "2023-01-02",
        "trdcnt1": "0",
        "trdcnt2": "0",
        "trdcnt3": "687",
        "trdcnt4": "139",
        "trdcnt5": "0",
        "trdcnt6": "-1",
        "trdcnt7": "0",
        "trdcnt8": "0",
        "trdcnt9": "-2,665",
        "trdcnt10": "1,696",
        "trdcnt11": "144",
        "trdcnt_tot": "0",
        "current_datetime": "2024-07-25 17:38:57.376179"
    },
    {
        "isinCd": "KR7419120001",
        "srtnCd": "A419120",
        "itmsNm": "\uc0b0\ub3cc",
        "trd_dd": "2022-12-29",
        "trdcnt1": "0",
        "trdcnt2": "0",
        "trdcnt3": "572",
        "trdcnt4": "0",
        "trdcnt5": "0",
        "trdcnt6": "0",
        "trdcnt7": "0",
        "trdcnt8": "300",
        "trdcnt9": "2,902",
        "trdcnt10": "-3,881",
        "trdcnt11": "107",
        "trdcnt_tot": "0",
        "current_datetime": "2024-07-25 17:38:57.465497"
    },
    {
        "isinCd": "KR7419120001",
        "srtnCd": "A419120",
        "itmsNm": "\uc0b0\ub3cc",
        "trd_dd": "2022-12-28",
        "trdcnt1": "0",
        "trdcnt2": "0",
        "trdcnt3": "500",
        "trdcnt4": "0",
        "trdcnt5": "0",
        "trdcnt6": "0",
        "trdcnt7": "0",
        "trdcnt8": "0",
        "trdcnt9": "2,206",
        "trdcnt10": "-2,735",
        "trdcnt11": "29",
        "trdcnt_tot": "0",
        "current_datetime": "2024-07-25 17:38:57.604190"
    },
    {
        "isinCd": "KR7419120001",
        "srtnCd": "A419120",
        "itmsNm": "\uc0b0\ub3cc",
        "trd_dd": "2022-12-27",
        "trdcnt1": "0",
        "trdcnt2": "0",
        "trdcnt3": "34",
        "trdcnt4": "608",
        "trdcnt5": "0",
        "trdcnt6": "0",
        "trdcnt7": "0",
        "trdcnt8": "-303",
        "trdcnt9": "-683",
        "trdcnt10": "382",
        "trdcnt11": "-38",
        "trdcnt_tot": "0",
        "current_datetime": "2024-07-25 17:38:57.670758"
    },
    {
        "isinCd": "KR7419120001",
        "srtnCd": "A419120",
        "itmsNm": "\uc0b0\ub3cc",
        "trd_dd": "2022-12-26",
        "trdcnt1": "0",
        "trdcnt2": "0",
        "trdcnt3": "-839",
        "trdcnt4": "0",
        "trdcnt5": "0",
        "trdcnt6": "1",
        "trdcnt7": "0",
        "trdcnt8": "300",
        "trdcnt9": "2,359",
        "trdcnt10": "-1,833",
        "trdcnt11": "12",
        "trdcnt_tot": "0",
        "current_datetime": "2024-07-25 17:38:57.757650"
    },
    {
        "isinCd": "KR7419120001",
        "srtnCd": "A419120",
        "itmsNm": "\uc0b0\ub3cc",
        "trd_dd": "2022-12-23",
        "trdcnt1": "201",
        "trdcnt2": "0",
        "trdcnt3": "-3,522",
        "trdcnt4": "-6,166",
        "trdcnt5": "0",
        "trdcnt6": "0",
        "trdcnt7": "0",
        "trdcnt8": "106",
        "trdcnt9": "8,048",
        "trdcnt10": "1,773",
        "trdcnt11": "-440",
        "trdcnt_tot": "0",
        "current_datetime": "2024-07-25 17:38:57.804024"
    },
    {
        "isinCd": "KR7419120001",
        "srtnCd": "A419120",
        "itmsNm": "\uc0b0\ub3cc",
        "trd_dd": "2022-12-22",
        "trdcnt1": "0",
        "trdcnt2": "0",
        "trdcnt3": "-37",
        "trdcnt4": "0",
        "trdcnt5": "0",
        "trdcnt6": "-6,389",
        "trdcnt7": "0",
        "trdcnt8": "0",
        "trdcnt9": "7,107",
        "trdcnt10": "-852",
        "trdcnt11": "171",
        "trdcnt_tot": "0",
        "current_datetime": "2024-07-25 17:38:57.821706"
    },
    {
        "isinCd": "KR7419120001",
        "srtnCd": "A419120",
        "itmsNm": "\uc0b0\ub3cc",
        "trd_dd": "2022-12-21",
        "trdcnt1": "0",
        "trdcnt2": "0",
        "trdcnt3": "1,412",
        "trdcnt4": "-19,135",
        "trdcnt5": "0",
        "trdcnt6": "-1,600",
        "trdcnt7": "0",
        "trdcnt8": "0",
        "trdcnt9": "31,095",
        "trdcnt10": "-11,341",
        "trdcnt11": "-431",
        "trdcnt_tot": "0",
        "current_datetime": "2024-07-25 17:38:57.888283"
    },
    {
        "isinCd": "KR7419120001",
        "srtnCd": "A419120",
        "itmsNm": "\uc0b0\ub3cc",
        "trd_dd": "2022-12-20",
        "trdcnt1": "0",
        "trdcnt2": "0",
        "trdcnt3": "23",
        "trdcnt4": "3,500",
        "trdcnt5": "0",
        "trdcnt6": "-2,000",
        "trdcnt7": "0",
        "trdcnt8": "0",
        "trdcnt9": "11,523",
        "trdcnt10": "-13,103",
        "trdcnt11": "57",
        "trdcnt_tot": "0",
        "current_datetime": "2024-07-25 17:38:57.978964"
    },
    {
        "isinCd": "KR7419120001",
        "srtnCd": "A419120",
        "itmsNm": "\uc0b0\ub3cc",
        "trd_dd": "2022-12-19",
        "trdcnt1": "-295",
        "trdcnt2": "0",
        "trdcnt3": "2,808",
        "trdcnt4": "3,500",
        "trdcnt5": "0",
        "trdcnt6": "-3,600",
        "trdcnt7": "0",
        "trdcnt8": "1",
        "trdcnt9": "-513",
        "trdcnt10": "-1,901",
        "trdcnt11": "0",
        "trdcnt_tot": "0",
        "current_datetime": "2024-07-25 17:38:58.178739"
    },
    {
        "isinCd": "KR7419120001",
        "srtnCd": "A419120",
        "itmsNm": "\uc0b0\ub3cc",
        "trd_dd": "2022-12-16",
        "trdcnt1": "0",
        "trdcnt2": "0",
        "trdcnt3": "2,606",
        "trdcnt4": "0",
        "trdcnt5": "0",
        "trdcnt6": "-2,000",
        "trdcnt7": "0",
        "trdcnt8": "0",
        "trdcnt9": "3,178",
        "trdcnt10": "-3,711",
        "trdcnt11": "-73",
        "trdcnt_tot": "0",
        "current_datetime": "2024-07-25 17:38:58.300620"
    },
    {
        "isinCd": "KR7419120001",
        "srtnCd": "A419120",
        "itmsNm": "\uc0b0\ub3cc",
        "trd_dd": "2022-12-15",
        "trdcnt1": "-500",
        "trdcnt2": "0",
        "trdcnt3": "3,104",
        "trdcnt4": "-387",
        "trdcnt5": "0",
        "trdcnt6": "-3,600",
        "trdcnt7": "0",
        "trdcnt8": "0",
        "trdcnt9": "-7,129",
        "trdcnt10": "8,754",
        "trdcnt11": "-242",
        "trdcnt_tot": "0",
        "current_datetime": "2024-07-25 17:38:58.380029"
    },
    {
        "isinCd": "KR7419120001",
        "srtnCd": "A419120",
        "itmsNm": "\uc0b0\ub3cc",
        "trd_dd": "2022-12-14",
        "trdcnt1": "0",
        "trdcnt2": "0",
        "trdcnt3": "763",
        "trdcnt4": "0",
        "trdcnt5": "0",
        "trdcnt6": "-5,600",
        "trdcnt7": "0",
        "trdcnt8": "0",
        "trdcnt9": "-251",
        "trdcnt10": "5,284",
        "trdcnt11": "-196",
        "trdcnt_tot": "0",
        "current_datetime": "2024-07-25 17:38:58.513250"
    },
    {
        "isinCd": "KR7419120001",
        "srtnCd": "A419120",
        "itmsNm": "\uc0b0\ub3cc",
        "trd_dd": "2022-12-13",
        "trdcnt1": "0",
        "trdcnt2": "0",
        "trdcnt3": "2,860",
        "trdcnt4": "-574",
        "trdcnt5": "0",
        "trdcnt6": "-4,000",
        "trdcnt7": "0",
        "trdcnt8": "0",
        "trdcnt9": "956",
        "trdcnt10": "771",
        "trdcnt11": "-13",
        "trdcnt_tot": "0",
        "current_datetime": "2024-07-25 17:38:58.641808"
    },
    {
        "isinCd": "KR7419120001",
        "srtnCd": "A419120",
        "itmsNm": "\uc0b0\ub3cc",
        "trd_dd": "2022-12-12",
        "trdcnt1": "0",
        "trdcnt2": "0",
        "trdcnt3": "0",
        "trdcnt4": "0",
        "trdcnt5": "0",
        "trdcnt6": "-6,000",
        "trdcnt7": "0",
        "trdcnt8": "0",
        "trdcnt9": "-3,585",
        "trdcnt10": "9,583",
        "trdcnt11": "2",
        "trdcnt_tot": "0",
        "current_datetime": "2024-07-25 17:38:58.823679"
    },
    {
        "isinCd": "KR7419120001",
        "srtnCd": "A419120",
        "itmsNm": "\uc0b0\ub3cc",
        "trd_dd": "2022-12-09",
        "trdcnt1": "226",
        "trdcnt2": "0",
        "trdcnt3": "0",
        "trdcnt4": "0",
        "trdcnt5": "0",
        "trdcnt6": "-1,200",
        "trdcnt7": "0",
        "trdcnt8": "0",
        "trdcnt9": "2,126",
        "trdcnt10": "-1,152",
        "trdcnt11": "0",
        "trdcnt_tot": "0",
        "current_datetime": "2024-07-25 17:38:58.889903"
    },
    {
        "isinCd": "KR7419120001",
        "srtnCd": "A419120",
        "itmsNm": "\uc0b0\ub3cc",
        "trd_dd": "2022-12-08",
        "trdcnt1": "1",
        "trdcnt2": "0",
        "trdcnt3": "500",
        "trdcnt4": "2,278",
        "trdcnt5": "0",
        "trdcnt6": "-14,400",
        "trdcnt7": "0",
        "trdcnt8": "1,089",
        "trdcnt9": "5,795",
        "trdcnt10": "4,737",
        "trdcnt11": "0",
        "trdcnt_tot": "0",
        "current_datetime": "2024-07-25 17:38:58.925866"
    },
    {
        "isinCd": "KR7419120001",
        "srtnCd": "A419120",
        "itmsNm": "\uc0b0\ub3cc",
        "trd_dd": "2022-12-07",
        "trdcnt1": "0",
        "trdcnt2": "0",
        "trdcnt3": "712",
        "trdcnt4": "123",
        "trdcnt5": "0",
        "trdcnt6": "-6,200",
        "trdcnt7": "0",
        "trdcnt8": "0",
        "trdcnt9": "15,224",
        "trdcnt10": "-9,883",
        "trdcnt11": "24",
        "trdcnt_tot": "0",
        "current_datetime": "2024-07-25 17:38:59.020998"
    },
    {
        "isinCd": "KR7419120001",
        "srtnCd": "A419120",
        "itmsNm": "\uc0b0\ub3cc",
        "trd_dd": "2022-12-06",
        "trdcnt1": "0",
        "trdcnt2": "0",
        "trdcnt3": "0",
        "trdcnt4": "0",
        "trdcnt5": "0",
        "trdcnt6": "-9,201",
        "trdcnt7": "0",
        "trdcnt8": "0",
        "trdcnt9": "10,183",
        "trdcnt10": "-1,088",
        "trdcnt11": "106",
        "trdcnt_tot": "0",
        "current_datetime": "2024-07-25 17:38:59.113125"
    },
    {
        "isinCd": "KR7419120001",
        "srtnCd": "A419120",
        "itmsNm": "\uc0b0\ub3cc",
        "trd_dd": "2022-12-05",
        "trdcnt1": "102",
        "trdcnt2": "0",
        "trdcnt3": "0",
        "trdcnt4": "0",
        "trdcnt5": "0",
        "trdcnt6": "-4,400",
        "trdcnt7": "0",
        "trdcnt8": "0",
        "trdcnt9": "5,013",
        "trdcnt10": "-725",
        "trdcnt11": "10",
        "trdcnt_tot": "0",
        "current_datetime": "2024-07-25 17:38:59.209135"
    },
    {
        "isinCd": "KR7419120001",
        "srtnCd": "A419120",
        "itmsNm": "\uc0b0\ub3cc",
        "trd_dd": "2022-12-02",
        "trdcnt1": "1",
        "trdcnt2": "0",
        "trdcnt3": "0",
        "trdcnt4": "21",
        "trdcnt5": "0",
        "trdcnt6": "-10,799",
        "trdcnt7": "0",
        "trdcnt8": "0",
        "trdcnt9": "5,105",
        "trdcnt10": "4,813",
        "trdcnt11": "859",
        "trdcnt_tot": "0",
        "current_datetime": "2024-07-25 17:38:59.258983"
    },
    {
        "isinCd": "KR7419120001",
        "srtnCd": "A419120",
        "itmsNm": "\uc0b0\ub3cc",
        "trd_dd": "2022-12-01",
        "trdcnt1": "1,001",
        "trdcnt2": "0",
        "trdcnt3": "0",
        "trdcnt4": "0",
        "trdcnt5": "0",
        "trdcnt6": "-12,000",
        "trdcnt7": "0",
        "trdcnt8": "0",
        "trdcnt9": "3,003",
        "trdcnt10": "7,652",
        "trdcnt11": "344",
        "trdcnt_tot": "0",
        "current_datetime": "2024-07-25 17:38:59.387710"
    },
    {
        "isinCd": "KR7419120001",
        "srtnCd": "A419120",
        "itmsNm": "\uc0b0\ub3cc",
        "trd_dd": "2022-11-30",
        "trdcnt1": "5",
        "trdcnt2": "0",
        "trdcnt3": "0",
        "trdcnt4": "0",
        "trdcnt5": "0",
        "trdcnt6": "-4,999",
        "trdcnt7": "0",
        "trdcnt8": "0",
        "trdcnt9": "1,333",
        "trdcnt10": "3,155",
        "trdcnt11": "506",
        "trdcnt_tot": "0",
        "current_datetime": "2024-07-25 17:38:59.519732"
    },
    {
        "isinCd": "KR7419120001",
        "srtnCd": "A419120",
        "itmsNm": "\uc0b0\ub3cc",
        "trd_dd": "2022-11-29",
        "trdcnt1": "372",
        "trdcnt2": "0",
        "trdcnt3": "-3,026",
        "trdcnt4": "213",
        "trdcnt5": "0",
        "trdcnt6": "-14,794",
        "trdcnt7": "0",
        "trdcnt8": "200",
        "trdcnt9": "13,371",
        "trdcnt10": "3,529",
        "trdcnt11": "135",
        "trdcnt_tot": "0",
        "current_datetime": "2024-07-25 17:38:59.581743"
    },
    {
        "isinCd": "KR7419120001",
        "srtnCd": "A419120",
        "itmsNm": "\uc0b0\ub3cc",
        "trd_dd": "2022-11-28",
        "trdcnt1": "200",
        "trdcnt2": "0",
        "trdcnt3": "0",
        "trdcnt4": "0",
        "trdcnt5": "0",
        "trdcnt6": "-21,206",
        "trdcnt7": "0",
        "trdcnt8": "400",
        "trdcnt9": "23,864",
        "trdcnt10": "-3,615",
        "trdcnt11": "357",
        "trdcnt_tot": "0",
        "current_datetime": "2024-07-25 17:38:59.671536"
    },
    {
        "isinCd": "KR7419120001",
        "srtnCd": "A419120",
        "itmsNm": "\uc0b0\ub3cc",
        "trd_dd": "2022-11-25",
        "trdcnt1": "-70",
        "trdcnt2": "0",
        "trdcnt3": "1,951",
        "trdcnt4": "0",
        "trdcnt5": "0",
        "trdcnt6": "0",
        "trdcnt7": "0",
        "trdcnt8": "0",
        "trdcnt9": "9,441",
        "trdcnt10": "-8,400",
        "trdcnt11": "-2,922",
        "trdcnt_tot": "0",
        "current_datetime": "2024-07-25 17:38:59.710897"
    },
    {
        "isinCd": "KR7419120001",
        "srtnCd": "A419120",
        "itmsNm": "\uc0b0\ub3cc",
        "trd_dd": "2022-11-24",
        "trdcnt1": "-3,930",
        "trdcnt2": "0",
        "trdcnt3": "-781",
        "trdcnt4": "514",
        "trdcnt5": "0",
        "trdcnt6": "0",
        "trdcnt7": "0",
        "trdcnt8": "-658",
        "trdcnt9": "1,188",
        "trdcnt10": "3,537",
        "trdcnt11": "130",
        "trdcnt_tot": "0",
        "current_datetime": "2024-07-25 17:38:59.752426"
    },
    {
        "isinCd": "KR7419120001",
        "srtnCd": "A419120",
        "itmsNm": "\uc0b0\ub3cc",
        "trd_dd": "2022-11-23",
        "trdcnt1": "0",
        "trdcnt2": "0",
        "trdcnt3": "0",
        "trdcnt4": "0",
        "trdcnt5": "0",
        "trdcnt6": "0",
        "trdcnt7": "0",
        "trdcnt8": "-582",
        "trdcnt9": "-1,235",
        "trdcnt10": "956",
        "trdcnt11": "861",
        "trdcnt_tot": "0",
        "current_datetime": "2024-07-25 17:38:59.797474"
    },
    {
        "isinCd": "KR7419120001",
        "srtnCd": "A419120",
        "itmsNm": "\uc0b0\ub3cc",
        "trd_dd": "2022-11-22",
        "trdcnt1": "-7,689",
        "trdcnt2": "0",
        "trdcnt3": "0",
        "trdcnt4": "0",
        "trdcnt5": "0",
        "trdcnt6": "0",
        "trdcnt7": "0",
        "trdcnt8": "-1,362",
        "trdcnt9": "10,125",
        "trdcnt10": "-1,096",
        "trdcnt11": "22",
        "trdcnt_tot": "0",
        "current_datetime": "2024-07-25 17:38:59.925874"
    },
    {
        "isinCd": "KR7419120001",
        "srtnCd": "A419120",
        "itmsNm": "\uc0b0\ub3cc",
        "trd_dd": "2022-11-21",
        "trdcnt1": "0",
        "trdcnt2": "0",
        "trdcnt3": "0",
        "trdcnt4": "-12,255",
        "trdcnt5": "0",
        "trdcnt6": "0",
        "trdcnt7": "0",
        "trdcnt8": "138",
        "trdcnt9": "11,902",
        "trdcnt10": "-922",
        "trdcnt11": "1,137",
        "trdcnt_tot": "0",
        "current_datetime": "2024-07-25 17:38:59.976161"
    },
    {
        "isinCd": "KR7419120001",
        "srtnCd": "A419120",
        "itmsNm": "\uc0b0\ub3cc",
        "trd_dd": "2022-11-18",
        "trdcnt1": "200",
        "trdcnt2": "0",
        "trdcnt3": "0",
        "trdcnt4": "0",
        "trdcnt5": "0",
        "trdcnt6": "0",
        "trdcnt7": "0",
        "trdcnt8": "2,100",
        "trdcnt9": "-3,193",
        "trdcnt10": "-110",
        "trdcnt11": "1,003",
        "trdcnt_tot": "0",
        "current_datetime": "2024-07-25 17:39:00.018145"
    },
    {
        "isinCd": "KR7419120001",
        "srtnCd": "A419120",
        "itmsNm": "\uc0b0\ub3cc",
        "trd_dd": "2022-11-17",
        "trdcnt1": "0",
        "trdcnt2": "0",
        "trdcnt3": "0",
        "trdcnt4": "0",
        "trdcnt5": "0",
        "trdcnt6": "0",
        "trdcnt7": "0",
        "trdcnt8": "0",
        "trdcnt9": "919",
        "trdcnt10": "-640",
        "trdcnt11": "-279",
        "trdcnt_tot": "0",
        "current_datetime": "2024-07-25 17:39:00.093640"
    },
    {
        "isinCd": "KR7419120001",
        "srtnCd": "A419120",
        "itmsNm": "\uc0b0\ub3cc",
        "trd_dd": "2022-11-16",
        "trdcnt1": "0",
        "trdcnt2": "0",
        "trdcnt3": "0",
        "trdcnt4": "0",
        "trdcnt5": "0",
        "trdcnt6": "0",
        "trdcnt7": "0",
        "trdcnt8": "0",
        "trdcnt9": "66",
        "trdcnt10": "102",
        "trdcnt11": "-168",
        "trdcnt_tot": "0",
        "current_datetime": "2024-07-25 17:39:00.135898"
    },
    {
        "isinCd": "KR7419120001",
        "srtnCd": "A419120",
        "itmsNm": "\uc0b0\ub3cc",
        "trd_dd": "2022-11-15",
        "trdcnt1": "0",
        "trdcnt2": "0",
        "trdcnt3": "0",
        "trdcnt4": "1,500",
        "trdcnt5": "0",
        "trdcnt6": "1",
        "trdcnt7": "0",
        "trdcnt8": "0",
        "trdcnt9": "-2,203",
        "trdcnt10": "-287",
        "trdcnt11": "989",
        "trdcnt_tot": "0",
        "current_datetime": "2024-07-25 17:39:00.211686"
    },
    {
        "isinCd": "KR7419120001",
        "srtnCd": "A419120",
        "itmsNm": "\uc0b0\ub3cc",
        "trd_dd": "2022-11-14",
        "trdcnt1": "0",
        "trdcnt2": "0",
        "trdcnt3": "2,464",
        "trdcnt4": "0",
        "trdcnt5": "0",
        "trdcnt6": "1",
        "trdcnt7": "0",
        "trdcnt8": "-300",
        "trdcnt9": "2,933",
        "trdcnt10": "-4,738",
        "trdcnt11": "-360",
        "trdcnt_tot": "0",
        "current_datetime": "2024-07-25 17:39:00.357725"
    },
    {
        "isinCd": "KR7419120001",
        "srtnCd": "A419120",
        "itmsNm": "\uc0b0\ub3cc",
        "trd_dd": "2022-11-11",
        "trdcnt1": "0",
        "trdcnt2": "0",
        "trdcnt3": "0",
        "trdcnt4": "0",
        "trdcnt5": "0",
        "trdcnt6": "0",
        "trdcnt7": "0",
        "trdcnt8": "-1",
        "trdcnt9": "2,914",
        "trdcnt10": "-3,004",
        "trdcnt11": "91",
        "trdcnt_tot": "0",
        "current_datetime": "2024-07-25 17:39:00.433127"
    },
    {
        "isinCd": "KR7419120001",
        "srtnCd": "A419120",
        "itmsNm": "\uc0b0\ub3cc",
        "trd_dd": "2022-11-10",
        "trdcnt1": "585",
        "trdcnt2": "0",
        "trdcnt3": "1,169",
        "trdcnt4": "591",
        "trdcnt5": "0",
        "trdcnt6": "0",
        "trdcnt7": "0",
        "trdcnt8": "1",
        "trdcnt9": "-24,254",
        "trdcnt10": "20,775",
        "trdcnt11": "1,133",
        "trdcnt_tot": "0",
        "current_datetime": "2024-07-25 17:39:00.518288"
    },
    {
        "isinCd": "KR7419120001",
        "srtnCd": "A419120",
        "itmsNm": "\uc0b0\ub3cc",
        "trd_dd": "2022-11-09",
        "trdcnt1": "0",
        "trdcnt2": "0",
        "trdcnt3": "0",
        "trdcnt4": "0",
        "trdcnt5": "0",
        "trdcnt6": "0",
        "trdcnt7": "0",
        "trdcnt8": "0",
        "trdcnt9": "12,031",
        "trdcnt10": "-12,031",
        "trdcnt11": "0",
        "trdcnt_tot": "0",
        "current_datetime": "2024-07-25 17:39:00.574365"
    },
    {
        "isinCd": "KR7419120001",
        "srtnCd": "A419120",
        "itmsNm": "\uc0b0\ub3cc",
        "trd_dd": "2022-11-08",
        "trdcnt1": "0",
        "trdcnt2": "0",
        "trdcnt3": "0",
        "trdcnt4": "0",
        "trdcnt5": "0",
        "trdcnt6": "0",
        "trdcnt7": "0",
        "trdcnt8": "-2,438",
        "trdcnt9": "-9,125",
        "trdcnt10": "11,649",
        "trdcnt11": "-86",
        "trdcnt_tot": "0",
        "current_datetime": "2024-07-25 17:39:00.751081"
    },
    {
        "isinCd": "KR7419120001",
        "srtnCd": "A419120",
        "itmsNm": "\uc0b0\ub3cc",
        "trd_dd": "2022-11-07",
        "trdcnt1": "0",
        "trdcnt2": "0",
        "trdcnt3": "0",
        "trdcnt4": "0",
        "trdcnt5": "0",
        "trdcnt6": "0",
        "trdcnt7": "0",
        "trdcnt8": "0",
        "trdcnt9": "3,827",
        "trdcnt10": "-3,927",
        "trdcnt11": "100",
        "trdcnt_tot": "0",
        "current_datetime": "2024-07-25 17:39:00.835591"
    },
    {
        "isinCd": "KR7419120001",
        "srtnCd": "A419120",
        "itmsNm": "\uc0b0\ub3cc",
        "trd_dd": "2022-11-04",
        "trdcnt1": "6,000",
        "trdcnt2": "0",
        "trdcnt3": "16",
        "trdcnt4": "-296",
        "trdcnt5": "0",
        "trdcnt6": "0",
        "trdcnt7": "0",
        "trdcnt8": "922",
        "trdcnt9": "-2,571",
        "trdcnt10": "-3,198",
        "trdcnt11": "-873",
        "trdcnt_tot": "0",
        "current_datetime": "2024-07-25 17:39:00.868787"
    },
    {
        "isinCd": "KR7419120001",
        "srtnCd": "A419120",
        "itmsNm": "\uc0b0\ub3cc",
        "trd_dd": "2022-11-03",
        "trdcnt1": "-400",
        "trdcnt2": "0",
        "trdcnt3": "0",
        "trdcnt4": "0",
        "trdcnt5": "0",
        "trdcnt6": "0",
        "trdcnt7": "0",
        "trdcnt8": "-830",
        "trdcnt9": "2,961",
        "trdcnt10": "-1,617",
        "trdcnt11": "-114",
        "trdcnt_tot": "0",
        "current_datetime": "2024-07-25 17:39:00.933649"
    },
    {
        "isinCd": "KR7419120001",
        "srtnCd": "A419120",
        "itmsNm": "\uc0b0\ub3cc",
        "trd_dd": "2022-11-02",
        "trdcnt1": "-200",
        "trdcnt2": "0",
        "trdcnt3": "0",
        "trdcnt4": "1,995",
        "trdcnt5": "0",
        "trdcnt6": "0",
        "trdcnt7": "0",
        "trdcnt8": "-4",
        "trdcnt9": "-13,507",
        "trdcnt10": "11,255",
        "trdcnt11": "461",
        "trdcnt_tot": "0",
        "current_datetime": "2024-07-25 17:39:01.000104"
    },
    {
        "isinCd": "KR7419120001",
        "srtnCd": "A419120",
        "itmsNm": "\uc0b0\ub3cc",
        "trd_dd": "2022-11-01",
        "trdcnt1": "5,200",
        "trdcnt2": "0",
        "trdcnt3": "500",
        "trdcnt4": "554",
        "trdcnt5": "0",
        "trdcnt6": "0",
        "trdcnt7": "0",
        "trdcnt8": "2,905",
        "trdcnt9": "-4,972",
        "trdcnt10": "-4,620",
        "trdcnt11": "433",
        "trdcnt_tot": "0",
        "current_datetime": "2024-07-25 17:39:01.085479"
    },
    {
        "isinCd": "KR7419120001",
        "srtnCd": "A419120",
        "itmsNm": "\uc0b0\ub3cc",
        "trd_dd": "2022-10-31",
        "trdcnt1": "1,001",
        "trdcnt2": "0",
        "trdcnt3": "0",
        "trdcnt4": "-9,000",
        "trdcnt5": "0",
        "trdcnt6": "0",
        "trdcnt7": "0",
        "trdcnt8": "-257",
        "trdcnt9": "10,199",
        "trdcnt10": "-2,012",
        "trdcnt11": "69",
        "trdcnt_tot": "0",
        "current_datetime": "2024-07-25 17:39:01.275224"
    },
    {
        "isinCd": "KR7419120001",
        "srtnCd": "A419120",
        "itmsNm": "\uc0b0\ub3cc",
        "trd_dd": "2022-10-28",
        "trdcnt1": "192",
        "trdcnt2": "0",
        "trdcnt3": "3,984",
        "trdcnt4": "29",
        "trdcnt5": "0",
        "trdcnt6": "-852",
        "trdcnt7": "0",
        "trdcnt8": "165",
        "trdcnt9": "4,095",
        "trdcnt10": "-6,095",
        "trdcnt11": "-1,518",
        "trdcnt_tot": "0",
        "current_datetime": "2024-07-25 17:39:01.410119"
    },
    {
        "isinCd": "KR7419120001",
        "srtnCd": "A419120",
        "itmsNm": "\uc0b0\ub3cc",
        "trd_dd": "2022-10-27",
        "trdcnt1": "-35,922",
        "trdcnt2": "-999",
        "trdcnt3": "-101,377",
        "trdcnt4": "-275,814",
        "trdcnt5": "-666",
        "trdcnt6": "-16,577",
        "trdcnt7": "-2,562",
        "trdcnt8": "-15,530",
        "trdcnt9": "535,238",
        "trdcnt10": "-88,483",
        "trdcnt11": "2,692",
        "trdcnt_tot": "0",
        "current_datetime": "2024-07-25 17:39:01.606732"
    },
    {
        "isinCd": "KR7419120001",
        "srtnCd": "A419120",
        "itmsNm": "\uc0b0\ub3cc",
        "trd_dd": "2023-01-05",
        "trdcnt1": "1,380",
        "trdcnt2": "0",
        "trdcnt3": "-61",
        "trdcnt4": "1,000",
        "trdcnt5": "0",
        "trdcnt6": "0",
        "trdcnt7": "0",
        "trdcnt8": "-1",
        "trdcnt9": "-5,736",
        "trdcnt10": "3,257",
        "trdcnt11": "161",
        "trdcnt_tot": "0",
        "current_datetime": "2024-07-26 02:46:49.245616"
    },
    {
        "isinCd": "KR7419120001",
        "srtnCd": "A419120",
        "itmsNm": "\uc0b0\ub3cc",
        "trd_dd": "2023-01-04",
        "trdcnt1": "4,971",
        "trdcnt2": "0",
        "trdcnt3": "0",
        "trdcnt4": "4,000",
        "trdcnt5": "0",
        "trdcnt6": "0",
        "trdcnt7": "0",
        "trdcnt8": "-6",
        "trdcnt9": "-13,790",
        "trdcnt10": "4,275",
        "trdcnt11": "550",
        "trdcnt_tot": "0",
        "current_datetime": "2024-07-26 02:46:49.329937"
    },
    {
        "isinCd": "KR7419120001",
        "srtnCd": "A419120",
        "itmsNm": "\uc0b0\ub3cc",
        "trd_dd": "2023-01-03",
        "trdcnt1": "0",
        "trdcnt2": "0",
        "trdcnt3": "219",
        "trdcnt4": "191",
        "trdcnt5": "0",
        "trdcnt6": "0",
        "trdcnt7": "0",
        "trdcnt8": "17",
        "trdcnt9": "-987",
        "trdcnt10": "717",
        "trdcnt11": "-157",
        "trdcnt_tot": "0",
        "current_datetime": "2024-07-26 02:46:49.413126"
    },
    {
        "isinCd": "KR7419120001",
        "srtnCd": "A419120",
        "itmsNm": "\uc0b0\ub3cc",
        "trd_dd": "2023-01-02",
        "trdcnt1": "0",
        "trdcnt2": "0",
        "trdcnt3": "687",
        "trdcnt4": "139",
        "trdcnt5": "0",
        "trdcnt6": "-1",
        "trdcnt7": "0",
        "trdcnt8": "0",
        "trdcnt9": "-2,665",
        "trdcnt10": "1,696",
        "trdcnt11": "144",
        "trdcnt_tot": "0",
        "current_datetime": "2024-07-26 02:46:49.466532"
    },
    {
        "isinCd": "KR7419120001",
        "srtnCd": "A419120",
        "itmsNm": "\uc0b0\ub3cc",
        "trd_dd": "2022-12-29",
        "trdcnt1": "0",
        "trdcnt2": "0",
        "trdcnt3": "572",
        "trdcnt4": "0",
        "trdcnt5": "0",
        "trdcnt6": "0",
        "trdcnt7": "0",
        "trdcnt8": "300",
        "trdcnt9": "2,902",
        "trdcnt10": "-3,881",
        "trdcnt11": "107",
        "trdcnt_tot": "0",
        "current_datetime": "2024-07-26 02:46:49.515876"
    },
    {
        "isinCd": "KR7419120001",
        "srtnCd": "A419120",
        "itmsNm": "\uc0b0\ub3cc",
        "trd_dd": "2022-12-28",
        "trdcnt1": "0",
        "trdcnt2": "0",
        "trdcnt3": "500",
        "trdcnt4": "0",
        "trdcnt5": "0",
        "trdcnt6": "0",
        "trdcnt7": "0",
        "trdcnt8": "0",
        "trdcnt9": "2,206",
        "trdcnt10": "-2,735",
        "trdcnt11": "29",
        "trdcnt_tot": "0",
        "current_datetime": "2024-07-26 02:46:49.601087"
    },
    {
        "isinCd": "KR7419120001",
        "srtnCd": "A419120",
        "itmsNm": "\uc0b0\ub3cc",
        "trd_dd": "2022-12-27",
        "trdcnt1": "0",
        "trdcnt2": "0",
        "trdcnt3": "34",
        "trdcnt4": "608",
        "trdcnt5": "0",
        "trdcnt6": "0",
        "trdcnt7": "0",
        "trdcnt8": "-303",
        "trdcnt9": "-683",
        "trdcnt10": "382",
        "trdcnt11": "-38",
        "trdcnt_tot": "0",
        "current_datetime": "2024-07-26 02:46:49.665761"
    },
    {
        "isinCd": "KR7419120001",
        "srtnCd": "A419120",
        "itmsNm": "\uc0b0\ub3cc",
        "trd_dd": "2022-12-26",
        "trdcnt1": "0",
        "trdcnt2": "0",
        "trdcnt3": "-839",
        "trdcnt4": "0",
        "trdcnt5": "0",
        "trdcnt6": "1",
        "trdcnt7": "0",
        "trdcnt8": "300",
        "trdcnt9": "2,359",
        "trdcnt10": "-1,833",
        "trdcnt11": "12",
        "trdcnt_tot": "0",
        "current_datetime": "2024-07-26 02:46:49.734676"
    },
    {
        "isinCd": "KR7419120001",
        "srtnCd": "A419120",
        "itmsNm": "\uc0b0\ub3cc",
        "trd_dd": "2022-12-23",
        "trdcnt1": "201",
        "trdcnt2": "0",
        "trdcnt3": "-3,522",
        "trdcnt4": "-6,166",
        "trdcnt5": "0",
        "trdcnt6": "0",
        "trdcnt7": "0",
        "trdcnt8": "106",
        "trdcnt9": "8,048",
        "trdcnt10": "1,773",
        "trdcnt11": "-440",
        "trdcnt_tot": "0",
        "current_datetime": "2024-07-26 02:46:49.859572"
    },
    {
        "isinCd": "KR7419120001",
        "srtnCd": "A419120",
        "itmsNm": "\uc0b0\ub3cc",
        "trd_dd": "2022-12-22",
        "trdcnt1": "0",
        "trdcnt2": "0",
        "trdcnt3": "-37",
        "trdcnt4": "0",
        "trdcnt5": "0",
        "trdcnt6": "-6,389",
        "trdcnt7": "0",
        "trdcnt8": "0",
        "trdcnt9": "7,107",
        "trdcnt10": "-852",
        "trdcnt11": "171",
        "trdcnt_tot": "0",
        "current_datetime": "2024-07-26 02:46:49.918468"
    },
    {
        "isinCd": "KR7419120001",
        "srtnCd": "A419120",
        "itmsNm": "\uc0b0\ub3cc",
        "trd_dd": "2022-12-21",
        "trdcnt1": "0",
        "trdcnt2": "0",
        "trdcnt3": "1,412",
        "trdcnt4": "-19,135",
        "trdcnt5": "0",
        "trdcnt6": "-1,600",
        "trdcnt7": "0",
        "trdcnt8": "0",
        "trdcnt9": "31,095",
        "trdcnt10": "-11,341",
        "trdcnt11": "-431",
        "trdcnt_tot": "0",
        "current_datetime": "2024-07-26 02:46:49.958503"
    },
    {
        "isinCd": "KR7419120001",
        "srtnCd": "A419120",
        "itmsNm": "\uc0b0\ub3cc",
        "trd_dd": "2022-12-20",
        "trdcnt1": "0",
        "trdcnt2": "0",
        "trdcnt3": "23",
        "trdcnt4": "3,500",
        "trdcnt5": "0",
        "trdcnt6": "-2,000",
        "trdcnt7": "0",
        "trdcnt8": "0",
        "trdcnt9": "11,523",
        "trdcnt10": "-13,103",
        "trdcnt11": "57",
        "trdcnt_tot": "0",
        "current_datetime": "2024-07-26 02:46:50.028340"
    },
    {
        "isinCd": "KR7419120001",
        "srtnCd": "A419120",
        "itmsNm": "\uc0b0\ub3cc",
        "trd_dd": "2022-12-19",
        "trdcnt1": "-295",
        "trdcnt2": "0",
        "trdcnt3": "2,808",
        "trdcnt4": "3,500",
        "trdcnt5": "0",
        "trdcnt6": "-3,600",
        "trdcnt7": "0",
        "trdcnt8": "1",
        "trdcnt9": "-513",
        "trdcnt10": "-1,901",
        "trdcnt11": "0",
        "trdcnt_tot": "0",
        "current_datetime": "2024-07-26 02:46:50.054294"
    },
    {
        "isinCd": "KR7419120001",
        "srtnCd": "A419120",
        "itmsNm": "\uc0b0\ub3cc",
        "trd_dd": "2022-12-16",
        "trdcnt1": "0",
        "trdcnt2": "0",
        "trdcnt3": "2,606",
        "trdcnt4": "0",
        "trdcnt5": "0",
        "trdcnt6": "-2,000",
        "trdcnt7": "0",
        "trdcnt8": "0",
        "trdcnt9": "3,178",
        "trdcnt10": "-3,711",
        "trdcnt11": "-73",
        "trdcnt_tot": "0",
        "current_datetime": "2024-07-26 02:46:50.135251"
    },
    {
        "isinCd": "KR7419120001",
        "srtnCd": "A419120",
        "itmsNm": "\uc0b0\ub3cc",
        "trd_dd": "2022-12-15",
        "trdcnt1": "-500",
        "trdcnt2": "0",
        "trdcnt3": "3,104",
        "trdcnt4": "-387",
        "trdcnt5": "0",
        "trdcnt6": "-3,600",
        "trdcnt7": "0",
        "trdcnt8": "0",
        "trdcnt9": "-7,129",
        "trdcnt10": "8,754",
        "trdcnt11": "-242",
        "trdcnt_tot": "0",
        "current_datetime": "2024-07-26 02:46:50.208858"
    },
    {
        "isinCd": "KR7419120001",
        "srtnCd": "A419120",
        "itmsNm": "\uc0b0\ub3cc",
        "trd_dd": "2022-12-14",
        "trdcnt1": "0",
        "trdcnt2": "0",
        "trdcnt3": "763",
        "trdcnt4": "0",
        "trdcnt5": "0",
        "trdcnt6": "-5,600",
        "trdcnt7": "0",
        "trdcnt8": "0",
        "trdcnt9": "-251",
        "trdcnt10": "5,284",
        "trdcnt11": "-196",
        "trdcnt_tot": "0",
        "current_datetime": "2024-07-26 02:46:50.273684"
    },
    {
        "isinCd": "KR7419120001",
        "srtnCd": "A419120",
        "itmsNm": "\uc0b0\ub3cc",
        "trd_dd": "2022-12-13",
        "trdcnt1": "0",
        "trdcnt2": "0",
        "trdcnt3": "2,860",
        "trdcnt4": "-574",
        "trdcnt5": "0",
        "trdcnt6": "-4,000",
        "trdcnt7": "0",
        "trdcnt8": "0",
        "trdcnt9": "956",
        "trdcnt10": "771",
        "trdcnt11": "-13",
        "trdcnt_tot": "0",
        "current_datetime": "2024-07-26 02:46:50.348966"
    },
    {
        "isinCd": "KR7419120001",
        "srtnCd": "A419120",
        "itmsNm": "\uc0b0\ub3cc",
        "trd_dd": "2022-12-12",
        "trdcnt1": "0",
        "trdcnt2": "0",
        "trdcnt3": "0",
        "trdcnt4": "0",
        "trdcnt5": "0",
        "trdcnt6": "-6,000",
        "trdcnt7": "0",
        "trdcnt8": "0",
        "trdcnt9": "-3,585",
        "trdcnt10": "9,583",
        "trdcnt11": "2",
        "trdcnt_tot": "0",
        "current_datetime": "2024-07-26 02:46:50.423229"
    },
    {
        "isinCd": "KR7419120001",
        "srtnCd": "A419120",
        "itmsNm": "\uc0b0\ub3cc",
        "trd_dd": "2022-12-09",
        "trdcnt1": "226",
        "trdcnt2": "0",
        "trdcnt3": "0",
        "trdcnt4": "0",
        "trdcnt5": "0",
        "trdcnt6": "-1,200",
        "trdcnt7": "0",
        "trdcnt8": "0",
        "trdcnt9": "2,126",
        "trdcnt10": "-1,152",
        "trdcnt11": "0",
        "trdcnt_tot": "0",
        "current_datetime": "2024-07-26 02:46:50.474758"
    },
    {
        "isinCd": "KR7419120001",
        "srtnCd": "A419120",
        "itmsNm": "\uc0b0\ub3cc",
        "trd_dd": "2022-12-08",
        "trdcnt1": "1",
        "trdcnt2": "0",
        "trdcnt3": "500",
        "trdcnt4": "2,278",
        "trdcnt5": "0",
        "trdcnt6": "-14,400",
        "trdcnt7": "0",
        "trdcnt8": "1,089",
        "trdcnt9": "5,795",
        "trdcnt10": "4,737",
        "trdcnt11": "0",
        "trdcnt_tot": "0",
        "current_datetime": "2024-07-26 02:46:50.525167"
    },
    {
        "isinCd": "KR7419120001",
        "srtnCd": "A419120",
        "itmsNm": "\uc0b0\ub3cc",
        "trd_dd": "2022-12-07",
        "trdcnt1": "0",
        "trdcnt2": "0",
        "trdcnt3": "712",
        "trdcnt4": "123",
        "trdcnt5": "0",
        "trdcnt6": "-6,200",
        "trdcnt7": "0",
        "trdcnt8": "0",
        "trdcnt9": "15,224",
        "trdcnt10": "-9,883",
        "trdcnt11": "24",
        "trdcnt_tot": "0",
        "current_datetime": "2024-07-26 02:46:50.651631"
    },
    {
        "isinCd": "KR7419120001",
        "srtnCd": "A419120",
        "itmsNm": "\uc0b0\ub3cc",
        "trd_dd": "2022-12-06",
        "trdcnt1": "0",
        "trdcnt2": "0",
        "trdcnt3": "0",
        "trdcnt4": "0",
        "trdcnt5": "0",
        "trdcnt6": "-9,201",
        "trdcnt7": "0",
        "trdcnt8": "0",
        "trdcnt9": "10,183",
        "trdcnt10": "-1,088",
        "trdcnt11": "106",
        "trdcnt_tot": "0",
        "current_datetime": "2024-07-26 02:46:50.731915"
    },
    {
        "isinCd": "KR7419120001",
        "srtnCd": "A419120",
        "itmsNm": "\uc0b0\ub3cc",
        "trd_dd": "2022-12-05",
        "trdcnt1": "102",
        "trdcnt2": "0",
        "trdcnt3": "0",
        "trdcnt4": "0",
        "trdcnt5": "0",
        "trdcnt6": "-4,400",
        "trdcnt7": "0",
        "trdcnt8": "0",
        "trdcnt9": "5,013",
        "trdcnt10": "-725",
        "trdcnt11": "10",
        "trdcnt_tot": "0",
        "current_datetime": "2024-07-26 02:46:50.766900"
    },
    {
        "isinCd": "KR7419120001",
        "srtnCd": "A419120",
        "itmsNm": "\uc0b0\ub3cc",
        "trd_dd": "2022-12-02",
        "trdcnt1": "1",
        "trdcnt2": "0",
        "trdcnt3": "0",
        "trdcnt4": "21",
        "trdcnt5": "0",
        "trdcnt6": "-10,799",
        "trdcnt7": "0",
        "trdcnt8": "0",
        "trdcnt9": "5,105",
        "trdcnt10": "4,813",
        "trdcnt11": "859",
        "trdcnt_tot": "0",
        "current_datetime": "2024-07-26 02:46:50.808324"
    },
    {
        "isinCd": "KR7419120001",
        "srtnCd": "A419120",
        "itmsNm": "\uc0b0\ub3cc",
        "trd_dd": "2022-12-01",
        "trdcnt1": "1,001",
        "trdcnt2": "0",
        "trdcnt3": "0",
        "trdcnt4": "0",
        "trdcnt5": "0",
        "trdcnt6": "-12,000",
        "trdcnt7": "0",
        "trdcnt8": "0",
        "trdcnt9": "3,003",
        "trdcnt10": "7,652",
        "trdcnt11": "344",
        "trdcnt_tot": "0",
        "current_datetime": "2024-07-26 02:46:50.856106"
    },
    {
        "isinCd": "KR7419120001",
        "srtnCd": "A419120",
        "itmsNm": "\uc0b0\ub3cc",
        "trd_dd": "2022-11-30",
        "trdcnt1": "5",
        "trdcnt2": "0",
        "trdcnt3": "0",
        "trdcnt4": "0",
        "trdcnt5": "0",
        "trdcnt6": "-4,999",
        "trdcnt7": "0",
        "trdcnt8": "0",
        "trdcnt9": "1,333",
        "trdcnt10": "3,155",
        "trdcnt11": "506",
        "trdcnt_tot": "0",
        "current_datetime": "2024-07-26 02:46:50.914690"
    },
    {
        "isinCd": "KR7419120001",
        "srtnCd": "A419120",
        "itmsNm": "\uc0b0\ub3cc",
        "trd_dd": "2022-11-29",
        "trdcnt1": "372",
        "trdcnt2": "0",
        "trdcnt3": "-3,026",
        "trdcnt4": "213",
        "trdcnt5": "0",
        "trdcnt6": "-14,794",
        "trdcnt7": "0",
        "trdcnt8": "200",
        "trdcnt9": "13,371",
        "trdcnt10": "3,529",
        "trdcnt11": "135",
        "trdcnt_tot": "0",
        "current_datetime": "2024-07-26 02:46:50.969187"
    },
    {
        "isinCd": "KR7419120001",
        "srtnCd": "A419120",
        "itmsNm": "\uc0b0\ub3cc",
        "trd_dd": "2022-11-28",
        "trdcnt1": "200",
        "trdcnt2": "0",
        "trdcnt3": "0",
        "trdcnt4": "0",
        "trdcnt5": "0",
        "trdcnt6": "-21,206",
        "trdcnt7": "0",
        "trdcnt8": "400",
        "trdcnt9": "23,864",
        "trdcnt10": "-3,615",
        "trdcnt11": "357",
        "trdcnt_tot": "0",
        "current_datetime": "2024-07-26 02:46:51.002434"
    },
    {
        "isinCd": "KR7419120001",
        "srtnCd": "A419120",
        "itmsNm": "\uc0b0\ub3cc",
        "trd_dd": "2022-11-25",
        "trdcnt1": "-70",
        "trdcnt2": "0",
        "trdcnt3": "1,951",
        "trdcnt4": "0",
        "trdcnt5": "0",
        "trdcnt6": "0",
        "trdcnt7": "0",
        "trdcnt8": "0",
        "trdcnt9": "9,441",
        "trdcnt10": "-8,400",
        "trdcnt11": "-2,922",
        "trdcnt_tot": "0",
        "current_datetime": "2024-07-26 02:46:51.071148"
    },
    {
        "isinCd": "KR7419120001",
        "srtnCd": "A419120",
        "itmsNm": "\uc0b0\ub3cc",
        "trd_dd": "2022-11-24",
        "trdcnt1": "-3,930",
        "trdcnt2": "0",
        "trdcnt3": "-781",
        "trdcnt4": "514",
        "trdcnt5": "0",
        "trdcnt6": "0",
        "trdcnt7": "0",
        "trdcnt8": "-658",
        "trdcnt9": "1,188",
        "trdcnt10": "3,537",
        "trdcnt11": "130",
        "trdcnt_tot": "0",
        "current_datetime": "2024-07-26 02:46:51.116787"
    },
    {
        "isinCd": "KR7419120001",
        "srtnCd": "A419120",
        "itmsNm": "\uc0b0\ub3cc",
        "trd_dd": "2022-11-23",
        "trdcnt1": "0",
        "trdcnt2": "0",
        "trdcnt3": "0",
        "trdcnt4": "0",
        "trdcnt5": "0",
        "trdcnt6": "0",
        "trdcnt7": "0",
        "trdcnt8": "-582",
        "trdcnt9": "-1,235",
        "trdcnt10": "956",
        "trdcnt11": "861",
        "trdcnt_tot": "0",
        "current_datetime": "2024-07-26 02:46:51.165141"
    },
    {
        "isinCd": "KR7419120001",
        "srtnCd": "A419120",
        "itmsNm": "\uc0b0\ub3cc",
        "trd_dd": "2022-11-22",
        "trdcnt1": "-7,689",
        "trdcnt2": "0",
        "trdcnt3": "0",
        "trdcnt4": "0",
        "trdcnt5": "0",
        "trdcnt6": "0",
        "trdcnt7": "0",
        "trdcnt8": "-1,362",
        "trdcnt9": "10,125",
        "trdcnt10": "-1,096",
        "trdcnt11": "22",
        "trdcnt_tot": "0",
        "current_datetime": "2024-07-26 02:46:51.204972"
    },
    {
        "isinCd": "KR7419120001",
        "srtnCd": "A419120",
        "itmsNm": "\uc0b0\ub3cc",
        "trd_dd": "2022-11-21",
        "trdcnt1": "0",
        "trdcnt2": "0",
        "trdcnt3": "0",
        "trdcnt4": "-12,255",
        "trdcnt5": "0",
        "trdcnt6": "0",
        "trdcnt7": "0",
        "trdcnt8": "138",
        "trdcnt9": "11,902",
        "trdcnt10": "-922",
        "trdcnt11": "1,137",
        "trdcnt_tot": "0",
        "current_datetime": "2024-07-26 02:46:51.243353"
    },
    {
        "isinCd": "KR7419120001",
        "srtnCd": "A419120",
        "itmsNm": "\uc0b0\ub3cc",
        "trd_dd": "2022-11-18",
        "trdcnt1": "200",
        "trdcnt2": "0",
        "trdcnt3": "0",
        "trdcnt4": "0",
        "trdcnt5": "0",
        "trdcnt6": "0",
        "trdcnt7": "0",
        "trdcnt8": "2,100",
        "trdcnt9": "-3,193",
        "trdcnt10": "-110",
        "trdcnt11": "1,003",
        "trdcnt_tot": "0",
        "current_datetime": "2024-07-26 02:46:51.334011"
    },
    {
        "isinCd": "KR7419120001",
        "srtnCd": "A419120",
        "itmsNm": "\uc0b0\ub3cc",
        "trd_dd": "2022-11-17",
        "trdcnt1": "0",
        "trdcnt2": "0",
        "trdcnt3": "0",
        "trdcnt4": "0",
        "trdcnt5": "0",
        "trdcnt6": "0",
        "trdcnt7": "0",
        "trdcnt8": "0",
        "trdcnt9": "919",
        "trdcnt10": "-640",
        "trdcnt11": "-279",
        "trdcnt_tot": "0",
        "current_datetime": "2024-07-26 02:46:51.357956"
    },
    {
        "isinCd": "KR7419120001",
        "srtnCd": "A419120",
        "itmsNm": "\uc0b0\ub3cc",
        "trd_dd": "2022-11-16",
        "trdcnt1": "0",
        "trdcnt2": "0",
        "trdcnt3": "0",
        "trdcnt4": "0",
        "trdcnt5": "0",
        "trdcnt6": "0",
        "trdcnt7": "0",
        "trdcnt8": "0",
        "trdcnt9": "66",
        "trdcnt10": "102",
        "trdcnt11": "-168",
        "trdcnt_tot": "0",
        "current_datetime": "2024-07-26 02:46:51.397472"
    },
    {
        "isinCd": "KR7419120001",
        "srtnCd": "A419120",
        "itmsNm": "\uc0b0\ub3cc",
        "trd_dd": "2022-11-15",
        "trdcnt1": "0",
        "trdcnt2": "0",
        "trdcnt3": "0",
        "trdcnt4": "1,500",
        "trdcnt5": "0",
        "trdcnt6": "1",
        "trdcnt7": "0",
        "trdcnt8": "0",
        "trdcnt9": "-2,203",
        "trdcnt10": "-287",
        "trdcnt11": "989",
        "trdcnt_tot": "0",
        "current_datetime": "2024-07-26 02:46:51.458778"
    },
    {
        "isinCd": "KR7419120001",
        "srtnCd": "A419120",
        "itmsNm": "\uc0b0\ub3cc",
        "trd_dd": "2022-11-14",
        "trdcnt1": "0",
        "trdcnt2": "0",
        "trdcnt3": "2,464",
        "trdcnt4": "0",
        "trdcnt5": "0",
        "trdcnt6": "1",
        "trdcnt7": "0",
        "trdcnt8": "-300",
        "trdcnt9": "2,933",
        "trdcnt10": "-4,738",
        "trdcnt11": "-360",
        "trdcnt_tot": "0",
        "current_datetime": "2024-07-26 02:46:51.544293"
    },
    {
        "isinCd": "KR7419120001",
        "srtnCd": "A419120",
        "itmsNm": "\uc0b0\ub3cc",
        "trd_dd": "2022-11-11",
        "trdcnt1": "0",
        "trdcnt2": "0",
        "trdcnt3": "0",
        "trdcnt4": "0",
        "trdcnt5": "0",
        "trdcnt6": "0",
        "trdcnt7": "0",
        "trdcnt8": "-1",
        "trdcnt9": "2,914",
        "trdcnt10": "-3,004",
        "trdcnt11": "91",
        "trdcnt_tot": "0",
        "current_datetime": "2024-07-26 02:46:51.618517"
    },
    {
        "isinCd": "KR7419120001",
        "srtnCd": "A419120",
        "itmsNm": "\uc0b0\ub3cc",
        "trd_dd": "2022-11-10",
        "trdcnt1": "585",
        "trdcnt2": "0",
        "trdcnt3": "1,169",
        "trdcnt4": "591",
        "trdcnt5": "0",
        "trdcnt6": "0",
        "trdcnt7": "0",
        "trdcnt8": "1",
        "trdcnt9": "-24,254",
        "trdcnt10": "20,775",
        "trdcnt11": "1,133",
        "trdcnt_tot": "0",
        "current_datetime": "2024-07-26 02:46:51.704928"
    },
    {
        "isinCd": "KR7419120001",
        "srtnCd": "A419120",
        "itmsNm": "\uc0b0\ub3cc",
        "trd_dd": "2022-11-09",
        "trdcnt1": "0",
        "trdcnt2": "0",
        "trdcnt3": "0",
        "trdcnt4": "0",
        "trdcnt5": "0",
        "trdcnt6": "0",
        "trdcnt7": "0",
        "trdcnt8": "0",
        "trdcnt9": "12,031",
        "trdcnt10": "-12,031",
        "trdcnt11": "0",
        "trdcnt_tot": "0",
        "current_datetime": "2024-07-26 02:46:51.783600"
    },
    {
        "isinCd": "KR7419120001",
        "srtnCd": "A419120",
        "itmsNm": "\uc0b0\ub3cc",
        "trd_dd": "2022-11-08",
        "trdcnt1": "0",
        "trdcnt2": "0",
        "trdcnt3": "0",
        "trdcnt4": "0",
        "trdcnt5": "0",
        "trdcnt6": "0",
        "trdcnt7": "0",
        "trdcnt8": "-2,438",
        "trdcnt9": "-9,125",
        "trdcnt10": "11,649",
        "trdcnt11": "-86",
        "trdcnt_tot": "0",
        "current_datetime": "2024-07-26 02:46:51.867382"
    },
    {
        "isinCd": "KR7419120001",
        "srtnCd": "A419120",
        "itmsNm": "\uc0b0\ub3cc",
        "trd_dd": "2022-11-07",
        "trdcnt1": "0",
        "trdcnt2": "0",
        "trdcnt3": "0",
        "trdcnt4": "0",
        "trdcnt5": "0",
        "trdcnt6": "0",
        "trdcnt7": "0",
        "trdcnt8": "0",
        "trdcnt9": "3,827",
        "trdcnt10": "-3,927",
        "trdcnt11": "100",
        "trdcnt_tot": "0",
        "current_datetime": "2024-07-26 02:46:51.995443"
    },
    {
        "isinCd": "KR7419120001",
        "srtnCd": "A419120",
        "itmsNm": "\uc0b0\ub3cc",
        "trd_dd": "2022-11-04",
        "trdcnt1": "6,000",
        "trdcnt2": "0",
        "trdcnt3": "16",
        "trdcnt4": "-296",
        "trdcnt5": "0",
        "trdcnt6": "0",
        "trdcnt7": "0",
        "trdcnt8": "922",
        "trdcnt9": "-2,571",
        "trdcnt10": "-3,198",
        "trdcnt11": "-873",
        "trdcnt_tot": "0",
        "current_datetime": "2024-07-26 02:46:52.074668"
    },
    {
        "isinCd": "KR7419120001",
        "srtnCd": "A419120",
        "itmsNm": "\uc0b0\ub3cc",
        "trd_dd": "2022-11-03",
        "trdcnt1": "-400",
        "trdcnt2": "0",
        "trdcnt3": "0",
        "trdcnt4": "0",
        "trdcnt5": "0",
        "trdcnt6": "0",
        "trdcnt7": "0",
        "trdcnt8": "-830",
        "trdcnt9": "2,961",
        "trdcnt10": "-1,617",
        "trdcnt11": "-114",
        "trdcnt_tot": "0",
        "current_datetime": "2024-07-26 02:46:52.148448"
    },
    {
        "isinCd": "KR7419120001",
        "srtnCd": "A419120",
        "itmsNm": "\uc0b0\ub3cc",
        "trd_dd": "2022-11-02",
        "trdcnt1": "-200",
        "trdcnt2": "0",
        "trdcnt3": "0",
        "trdcnt4": "1,995",
        "trdcnt5": "0",
        "trdcnt6": "0",
        "trdcnt7": "0",
        "trdcnt8": "-4",
        "trdcnt9": "-13,507",
        "trdcnt10": "11,255",
        "trdcnt11": "461",
        "trdcnt_tot": "0",
        "current_datetime": "2024-07-26 02:46:52.209693"
    },
    {
        "isinCd": "KR7419120001",
        "srtnCd": "A419120",
        "itmsNm": "\uc0b0\ub3cc",
        "trd_dd": "2022-11-01",
        "trdcnt1": "5,200",
        "trdcnt2": "0",
        "trdcnt3": "500",
        "trdcnt4": "554",
        "trdcnt5": "0",
        "trdcnt6": "0",
        "trdcnt7": "0",
        "trdcnt8": "2,905",
        "trdcnt9": "-4,972",
        "trdcnt10": "-4,620",
        "trdcnt11": "433",
        "trdcnt_tot": "0",
        "current_datetime": "2024-07-26 02:46:52.273020"
    },
    {
        "isinCd": "KR7419120001",
        "srtnCd": "A419120",
        "itmsNm": "\uc0b0\ub3cc",
        "trd_dd": "2022-10-31",
        "trdcnt1": "1,001",
        "trdcnt2": "0",
        "trdcnt3": "0",
        "trdcnt4": "-9,000",
        "trdcnt5": "0",
        "trdcnt6": "0",
        "trdcnt7": "0",
        "trdcnt8": "-257",
        "trdcnt9": "10,199",
        "trdcnt10": "-2,012",
        "trdcnt11": "69",
        "trdcnt_tot": "0",
        "current_datetime": "2024-07-26 02:46:52.313235"
    },
    {
        "isinCd": "KR7419120001",
        "srtnCd": "A419120",
        "itmsNm": "\uc0b0\ub3cc",
        "trd_dd": "2022-10-28",
        "trdcnt1": "192",
        "trdcnt2": "0",
        "trdcnt3": "3,984",
        "trdcnt4": "29",
        "trdcnt5": "0",
        "trdcnt6": "-852",
        "trdcnt7": "0",
        "trdcnt8": "165",
        "trdcnt9": "4,095",
        "trdcnt10": "-6,095",
        "trdcnt11": "-1,518",
        "trdcnt_tot": "0",
        "current_datetime": "2024-07-26 02:46:52.356666"
    },
    {
        "isinCd": "KR7419120001",
        "srtnCd": "A419120",
        "itmsNm": "\uc0b0\ub3cc",
        "trd_dd": "2022-10-27",
        "trdcnt1": "-35,922",
        "trdcnt2": "-999",
        "trdcnt3": "-101,377",
        "trdcnt4": "-275,814",
        "trdcnt5": "-666",
        "trdcnt6": "-16,577",
        "trdcnt7": "-2,562",
        "trdcnt8": "-15,530",
        "trdcnt9": "535,238",
        "trdcnt10": "-88,483",
        "trdcnt11": "2,692",
        "trdcnt_tot": "0",
        "current_datetime": "2024-07-26 02:46:52.390122"
    }
]